{
  "_poa": {
    "prev_file": "heartbeats_20251230_141039.json",
    "prev_sha256": "9a7e144bb3efdec273b68af3f926838d3b24586d20a18da6e071f67005e30601",
    "proof_version": "poa-exports-v1",
    "sequence": 3,
    "ts": "2025-12-30T14:20:02Z"
  },
  "data": {
    "1": {
      "beats": [
        {
          "down_count": 0,
          "duration": 60,
          "id": 8130,
          "important": false,
          "monitor_id": 1,
          "msg": "200 - OK",
          "ping": 14,
          "status": 1,
          "time": "2025-12-30 12:35:52.966"
        },
        {
          "down_count": 0,
          "duration": 60,
          "id": 8133,
          "important": false,
          "monitor_id": 1,
          "msg": "200 - OK",
          "ping": 10,
          "status": 1,
          "time": "2025-12-30 12:36:52.987"
        },
        {
          "down_count": 0,
          "duration": 60,
          "id": 8136,
          "important": false,
          "monitor_id": 1,
          "msg": "200 - OK",
          "ping": 11,
          "status": 1,
          "time": "2025-12-30 12:37:53.001"
        },
        {
          "down_count": 0,
          "duration": 60,
          "id": 8139,
          "important": false,
          "monitor_id": 1,
          "msg": "200 - OK",
          "ping": 14,
          "status": 1,
          "time": "2025-12-30 12:38:53.015"
        },
        {
          "down_count": 0,
          "duration": 60,
          "id": 8142,
          "important": false,
          "monitor_id": 1,
          "msg": "200 - OK",
          "ping": 14,
          "status": 1,
          "time": "2025-12-30 12:39:53.033"
        },
        {
          "down_count": 0,
          "duration": 60,
          "id": 8145,
          "important": false,
          "monitor_id": 1,
          "msg": "200 - OK",
          "ping": 11,
          "status": 1,
          "time": "2025-12-30 12:40:53.050"
        },
        {
          "down_count": 0,
          "duration": 60,
          "id": 8148,
          "important": false,
          "monitor_id": 1,
          "msg": "200 - OK",
          "ping": 16,
          "status": 1,
          "time": "2025-12-30 12:41:53.069"
        },
        {
          "down_count": 0,
          "duration": 60,
          "id": 8151,
          "important": false,
          "monitor_id": 1,
          "msg": "200 - OK",
          "ping": 10,
          "status": 1,
          "time": "2025-12-30 12:42:53.089"
        },
        {
          "down_count": 0,
          "duration": 60,
          "id": 8154,
          "important": false,
          "monitor_id": 1,
          "msg": "200 - OK",
          "ping": 14,
          "status": 1,
          "time": "2025-12-30 12:43:53.104"
        },
        {
          "down_count": 0,
          "duration": 60,
          "id": 8157,
          "important": false,
          "monitor_id": 1,
          "msg": "200 - OK",
          "ping": 10,
          "status": 1,
          "time": "2025-12-30 12:44:53.124"
        },
        {
          "down_count": 0,
          "duration": 60,
          "id": 8160,
          "important": false,
          "monitor_id": 1,
          "msg": "200 - OK",
          "ping": 13,
          "status": 1,
          "time": "2025-12-30 12:45:53.137"
        },
        {
          "down_count": 0,
          "duration": 60,
          "id": 8163,
          "important": false,
          "monitor_id": 1,
          "msg": "200 - OK",
          "ping": 21,
          "status": 1,
          "time": "2025-12-30 12:46:53.158"
        },
        {
          "down_count": 0,
          "duration": 60,
          "id": 8166,
          "important": false,
          "monitor_id": 1,
          "msg": "200 - OK",
          "ping": 19,
          "status": 1,
          "time": "2025-12-30 12:47:53.186"
        },
        {
          "down_count": 0,
          "duration": 60,
          "id": 8169,
          "important": false,
          "monitor_id": 1,
          "msg": "200 - OK",
          "ping": 15,
          "status": 1,
          "time": "2025-12-30 12:48:53.212"
        },
        {
          "down_count": 0,
          "duration": 60,
          "id": 8172,
          "important": false,
          "monitor_id": 1,
          "msg": "200 - OK",
          "ping": 28,
          "status": 1,
          "time": "2025-12-30 12:49:53.232"
        },
        {
          "down_count": 0,
          "duration": 60,
          "id": 8175,
          "important": false,
          "monitor_id": 1,
          "msg": "200 - OK",
          "ping": 16,
          "status": 1,
          "time": "2025-12-30 12:50:53.272"
        },
        {
          "down_count": 0,
          "duration": 60,
          "id": 8178,
          "important": false,
          "monitor_id": 1,
          "msg": "200 - OK",
          "ping": 24,
          "status": 1,
          "time": "2025-12-30 12:51:53.301"
        },
        {
          "down_count": 0,
          "duration": 60,
          "id": 8181,
          "important": false,
          "monitor_id": 1,
          "msg": "200 - OK",
          "ping": 15,
          "status": 1,
          "time": "2025-12-30 12:52:53.356"
        },
        {
          "down_count": 0,
          "duration": 60,
          "id": 8184,
          "important": false,
          "monitor_id": 1,
          "msg": "200 - OK",
          "ping": 14,
          "status": 1,
          "time": "2025-12-30 12:53:53.377"
        },
        {
          "down_count": 0,
          "duration": 60,
          "id": 8187,
          "important": false,
          "monitor_id": 1,
          "msg": "200 - OK",
          "ping": 12,
          "status": 1,
          "time": "2025-12-30 12:54:53.398"
        },
        {
          "down_count": 0,
          "duration": 60,
          "id": 8190,
          "important": false,
          "monitor_id": 1,
          "msg": "200 - OK",
          "ping": 12,
          "status": 1,
          "time": "2025-12-30 12:55:53.414"
        },
        {
          "down_count": 0,
          "duration": 60,
          "id": 8193,
          "important": false,
          "monitor_id": 1,
          "msg": "200 - OK",
          "ping": 18,
          "status": 1,
          "time": "2025-12-30 12:56:53.431"
        },
        {
          "down_count": 0,
          "duration": 60,
          "id": 8196,
          "important": false,
          "monitor_id": 1,
          "msg": "200 - OK",
          "ping": 18,
          "status": 1,
          "time": "2025-12-30 12:57:53.456"
        },
        {
          "down_count": 0,
          "duration": 60,
          "id": 8199,
          "important": false,
          "monitor_id": 1,
          "msg": "200 - OK",
          "ping": 16,
          "status": 1,
          "time": "2025-12-30 12:58:53.483"
        },
        {
          "down_count": 0,
          "duration": 60,
          "id": 8202,
          "important": false,
          "monitor_id": 1,
          "msg": "200 - OK",
          "ping": 12,
          "status": 1,
          "time": "2025-12-30 12:59:53.509"
        },
        {
          "down_count": 0,
          "duration": 60,
          "id": 8205,
          "important": false,
          "monitor_id": 1,
          "msg": "200 - OK",
          "ping": 10,
          "status": 1,
          "time": "2025-12-30 13:00:53.525"
        },
        {
          "down_count": 0,
          "duration": 60,
          "id": 8208,
          "important": false,
          "monitor_id": 1,
          "msg": "200 - OK",
          "ping": 11,
          "status": 1,
          "time": "2025-12-30 13:01:53.540"
        },
        {
          "down_count": 0,
          "duration": 60,
          "id": 8211,
          "important": false,
          "monitor_id": 1,
          "msg": "200 - OK",
          "ping": 14,
          "status": 1,
          "time": "2025-12-30 13:02:53.556"
        },
        {
          "down_count": 0,
          "duration": 60,
          "id": 8214,
          "important": false,
          "monitor_id": 1,
          "msg": "200 - OK",
          "ping": 12,
          "status": 1,
          "time": "2025-12-30 13:03:53.574"
        },
        {
          "down_count": 0,
          "duration": 60,
          "id": 8217,
          "important": false,
          "monitor_id": 1,
          "msg": "200 - OK",
          "ping": 14,
          "status": 1,
          "time": "2025-12-30 13:04:53.590"
        },
        {
          "down_count": 0,
          "duration": 60,
          "id": 8220,
          "important": false,
          "monitor_id": 1,
          "msg": "200 - OK",
          "ping": 13,
          "status": 1,
          "time": "2025-12-30 13:05:53.608"
        },
        {
          "down_count": 0,
          "duration": 60,
          "id": 8223,
          "important": false,
          "monitor_id": 1,
          "msg": "200 - OK",
          "ping": 12,
          "status": 1,
          "time": "2025-12-30 13:06:53.626"
        },
        {
          "down_count": 0,
          "duration": 60,
          "id": 8226,
          "important": false,
          "monitor_id": 1,
          "msg": "200 - OK",
          "ping": 11,
          "status": 1,
          "time": "2025-12-30 13:07:53.643"
        },
        {
          "down_count": 0,
          "duration": 60,
          "id": 8229,
          "important": false,
          "monitor_id": 1,
          "msg": "200 - OK",
          "ping": 12,
          "status": 1,
          "time": "2025-12-30 13:08:53.658"
        },
        {
          "down_count": 0,
          "duration": 60,
          "id": 8232,
          "important": false,
          "monitor_id": 1,
          "msg": "200 - OK",
          "ping": 110,
          "status": 1,
          "time": "2025-12-30 13:09:53.674"
        },
        {
          "down_count": 0,
          "duration": 60,
          "id": 8235,
          "important": false,
          "monitor_id": 1,
          "msg": "200 - OK",
          "ping": 16,
          "status": 1,
          "time": "2025-12-30 13:10:53.794"
        },
        {
          "down_count": 0,
          "duration": 60,
          "id": 8238,
          "important": false,
          "monitor_id": 1,
          "msg": "200 - OK",
          "ping": 41,
          "status": 1,
          "time": "2025-12-30 13:11:53.828"
        },
        {
          "down_count": 0,
          "duration": 60,
          "id": 8241,
          "important": false,
          "monitor_id": 1,
          "msg": "200 - OK",
          "ping": 12,
          "status": 1,
          "time": "2025-12-30 13:12:53.933"
        },
        {
          "down_count": 0,
          "duration": 60,
          "id": 8244,
          "important": false,
          "monitor_id": 1,
          "msg": "200 - OK",
          "ping": 13,
          "status": 1,
          "time": "2025-12-30 13:13:53.950"
        },
        {
          "down_count": 0,
          "duration": 60,
          "id": 8247,
          "important": false,
          "monitor_id": 1,
          "msg": "200 - OK",
          "ping": 13,
          "status": 1,
          "time": "2025-12-30 13:14:53.967"
        },
        {
          "down_count": 0,
          "duration": 60,
          "id": 8250,
          "important": false,
          "monitor_id": 1,
          "msg": "200 - OK",
          "ping": 15,
          "status": 1,
          "time": "2025-12-30 13:15:53.984"
        },
        {
          "down_count": 0,
          "duration": 60,
          "id": 8253,
          "important": false,
          "monitor_id": 1,
          "msg": "200 - OK",
          "ping": 12,
          "status": 1,
          "time": "2025-12-30 13:16:54.012"
        },
        {
          "down_count": 0,
          "duration": 60,
          "id": 8256,
          "important": false,
          "monitor_id": 1,
          "msg": "200 - OK",
          "ping": 17,
          "status": 1,
          "time": "2025-12-30 13:17:54.031"
        },
        {
          "down_count": 0,
          "duration": 60,
          "id": 8259,
          "important": false,
          "monitor_id": 1,
          "msg": "200 - OK",
          "ping": 14,
          "status": 1,
          "time": "2025-12-30 13:18:54.056"
        },
        {
          "down_count": 0,
          "duration": 60,
          "id": 8262,
          "important": false,
          "monitor_id": 1,
          "msg": "200 - OK",
          "ping": 28,
          "status": 1,
          "time": "2025-12-30 13:19:54.077"
        },
        {
          "down_count": 0,
          "duration": 60,
          "id": 8265,
          "important": false,
          "monitor_id": 1,
          "msg": "200 - OK",
          "ping": 21,
          "status": 1,
          "time": "2025-12-30 13:20:54.117"
        },
        {
          "down_count": 0,
          "duration": 60,
          "id": 8268,
          "important": false,
          "monitor_id": 1,
          "msg": "200 - OK",
          "ping": 20,
          "status": 1,
          "time": "2025-12-30 13:21:54.151"
        },
        {
          "down_count": 0,
          "duration": 60,
          "id": 8271,
          "important": false,
          "monitor_id": 1,
          "msg": "200 - OK",
          "ping": 17,
          "status": 1,
          "time": "2025-12-30 13:22:54.183"
        },
        {
          "down_count": 0,
          "duration": 60,
          "id": 8274,
          "important": false,
          "monitor_id": 1,
          "msg": "200 - OK",
          "ping": 21,
          "status": 1,
          "time": "2025-12-30 13:23:54.214"
        },
        {
          "down_count": 0,
          "duration": 60,
          "id": 8277,
          "important": false,
          "monitor_id": 1,
          "msg": "200 - OK",
          "ping": 15,
          "status": 1,
          "time": "2025-12-30 13:24:54.243"
        },
        {
          "down_count": 0,
          "duration": 60,
          "id": 8281,
          "important": false,
          "monitor_id": 1,
          "msg": "200 - OK",
          "ping": 24,
          "status": 1,
          "time": "2025-12-30 13:25:54.270"
        },
        {
          "down_count": 0,
          "duration": 60,
          "id": 8284,
          "important": false,
          "monitor_id": 1,
          "msg": "200 - OK",
          "ping": 14,
          "status": 1,
          "time": "2025-12-30 13:26:54.309"
        },
        {
          "down_count": 0,
          "duration": 60,
          "id": 8287,
          "important": false,
          "monitor_id": 1,
          "msg": "200 - OK",
          "ping": 14,
          "status": 1,
          "time": "2025-12-30 13:27:54.344"
        },
        {
          "down_count": 0,
          "duration": 60,
          "id": 8290,
          "important": false,
          "monitor_id": 1,
          "msg": "200 - OK",
          "ping": 11,
          "status": 1,
          "time": "2025-12-30 13:28:54.365"
        },
        {
          "down_count": 0,
          "duration": 60,
          "id": 8293,
          "important": false,
          "monitor_id": 1,
          "msg": "200 - OK",
          "ping": 12,
          "status": 1,
          "time": "2025-12-30 13:29:54.390"
        },
        {
          "down_count": 0,
          "duration": 60,
          "id": 8296,
          "important": false,
          "monitor_id": 1,
          "msg": "200 - OK",
          "ping": 8,
          "status": 1,
          "time": "2025-12-30 13:30:54.410"
        },
        {
          "down_count": 0,
          "duration": 60,
          "id": 8299,
          "important": false,
          "monitor_id": 1,
          "msg": "200 - OK",
          "ping": 11,
          "status": 1,
          "time": "2025-12-30 13:31:54.427"
        },
        {
          "down_count": 0,
          "duration": 60,
          "id": 8302,
          "important": false,
          "monitor_id": 1,
          "msg": "200 - OK",
          "ping": 9,
          "status": 1,
          "time": "2025-12-30 13:32:54.444"
        },
        {
          "down_count": 0,
          "duration": 60,
          "id": 8305,
          "important": false,
          "monitor_id": 1,
          "msg": "200 - OK",
          "ping": 12,
          "status": 1,
          "time": "2025-12-30 13:33:54.457"
        },
        {
          "down_count": 0,
          "duration": 60,
          "id": 8308,
          "important": false,
          "monitor_id": 1,
          "msg": "200 - OK",
          "ping": 16,
          "status": 1,
          "time": "2025-12-30 13:34:54.478"
        },
        {
          "down_count": 0,
          "duration": 60,
          "id": 8311,
          "important": false,
          "monitor_id": 1,
          "msg": "200 - OK",
          "ping": 9,
          "status": 1,
          "time": "2025-12-30 13:35:54.502"
        },
        {
          "down_count": 0,
          "duration": 60,
          "id": 8314,
          "important": false,
          "monitor_id": 1,
          "msg": "200 - OK",
          "ping": 9,
          "status": 1,
          "time": "2025-12-30 13:36:54.518"
        },
        {
          "down_count": 0,
          "duration": 60,
          "id": 8317,
          "important": false,
          "monitor_id": 1,
          "msg": "200 - OK",
          "ping": 9,
          "status": 1,
          "time": "2025-12-30 13:37:54.529"
        },
        {
          "down_count": 0,
          "duration": 60,
          "id": 8320,
          "important": false,
          "monitor_id": 1,
          "msg": "200 - OK",
          "ping": 9,
          "status": 1,
          "time": "2025-12-30 13:38:54.543"
        },
        {
          "down_count": 0,
          "duration": 60,
          "id": 8323,
          "important": false,
          "monitor_id": 1,
          "msg": "200 - OK",
          "ping": 10,
          "status": 1,
          "time": "2025-12-30 13:39:54.559"
        },
        {
          "down_count": 0,
          "duration": 60,
          "id": 8326,
          "important": false,
          "monitor_id": 1,
          "msg": "200 - OK",
          "ping": 8,
          "status": 1,
          "time": "2025-12-30 13:40:54.577"
        },
        {
          "down_count": 0,
          "duration": 60,
          "id": 8329,
          "important": false,
          "monitor_id": 1,
          "msg": "200 - OK",
          "ping": 10,
          "status": 1,
          "time": "2025-12-30 13:41:54.592"
        },
        {
          "down_count": 0,
          "duration": 60,
          "id": 8332,
          "important": false,
          "monitor_id": 1,
          "msg": "200 - OK",
          "ping": 11,
          "status": 1,
          "time": "2025-12-30 13:42:54.607"
        },
        {
          "down_count": 0,
          "duration": 60,
          "id": 8335,
          "important": false,
          "monitor_id": 1,
          "msg": "200 - OK",
          "ping": 11,
          "status": 1,
          "time": "2025-12-30 13:43:54.631"
        },
        {
          "down_count": 0,
          "duration": 60,
          "id": 8338,
          "important": false,
          "monitor_id": 1,
          "msg": "200 - OK",
          "ping": 8,
          "status": 1,
          "time": "2025-12-30 13:44:54.649"
        },
        {
          "down_count": 0,
          "duration": 60,
          "id": 8341,
          "important": false,
          "monitor_id": 1,
          "msg": "200 - OK",
          "ping": 10,
          "status": 1,
          "time": "2025-12-30 13:45:54.663"
        },
        {
          "down_count": 0,
          "duration": 60,
          "id": 8344,
          "important": false,
          "monitor_id": 1,
          "msg": "200 - OK",
          "ping": 9,
          "status": 1,
          "time": "2025-12-30 13:46:54.683"
        },
        {
          "down_count": 0,
          "duration": 60,
          "id": 8347,
          "important": false,
          "monitor_id": 1,
          "msg": "200 - OK",
          "ping": 11,
          "status": 1,
          "time": "2025-12-30 13:47:54.700"
        },
        {
          "down_count": 0,
          "duration": 60,
          "id": 8350,
          "important": false,
          "monitor_id": 1,
          "msg": "200 - OK",
          "ping": 8,
          "status": 1,
          "time": "2025-12-30 13:48:54.718"
        },
        {
          "down_count": 0,
          "duration": 60,
          "id": 8353,
          "important": false,
          "monitor_id": 1,
          "msg": "200 - OK",
          "ping": 9,
          "status": 1,
          "time": "2025-12-30 13:49:54.734"
        },
        {
          "down_count": 0,
          "duration": 60,
          "id": 8356,
          "important": false,
          "monitor_id": 1,
          "msg": "200 - OK",
          "ping": 14,
          "status": 1,
          "time": "2025-12-30 13:50:54.749"
        },
        {
          "down_count": 0,
          "duration": 60,
          "id": 8359,
          "important": false,
          "monitor_id": 1,
          "msg": "200 - OK",
          "ping": 10,
          "status": 1,
          "time": "2025-12-30 13:51:54.784"
        },
        {
          "down_count": 0,
          "duration": 60,
          "id": 8362,
          "important": false,
          "monitor_id": 1,
          "msg": "200 - OK",
          "ping": 11,
          "status": 1,
          "time": "2025-12-30 13:52:54.796"
        },
        {
          "down_count": 0,
          "duration": 60,
          "id": 8365,
          "important": false,
          "monitor_id": 1,
          "msg": "200 - OK",
          "ping": 8,
          "status": 1,
          "time": "2025-12-30 13:53:54.811"
        },
        {
          "down_count": 0,
          "duration": 60,
          "id": 8368,
          "important": false,
          "monitor_id": 1,
          "msg": "200 - OK",
          "ping": 8,
          "status": 1,
          "time": "2025-12-30 13:54:54.823"
        },
        {
          "down_count": 0,
          "duration": 60,
          "id": 8371,
          "important": false,
          "monitor_id": 1,
          "msg": "200 - OK",
          "ping": 11,
          "status": 1,
          "time": "2025-12-30 13:55:54.833"
        },
        {
          "down_count": 0,
          "duration": 60,
          "id": 8374,
          "important": false,
          "monitor_id": 1,
          "msg": "200 - OK",
          "ping": 8,
          "status": 1,
          "time": "2025-12-30 13:56:54.853"
        },
        {
          "down_count": 0,
          "duration": 60,
          "id": 8377,
          "important": false,
          "monitor_id": 1,
          "msg": "200 - OK",
          "ping": 13,
          "status": 1,
          "time": "2025-12-30 13:57:54.869"
        },
        {
          "down_count": 0,
          "duration": 60,
          "id": 8380,
          "important": false,
          "monitor_id": 1,
          "msg": "200 - OK",
          "ping": 12,
          "status": 1,
          "time": "2025-12-30 13:58:54.891"
        },
        {
          "down_count": 0,
          "duration": 60,
          "id": 8383,
          "important": false,
          "monitor_id": 1,
          "msg": "200 - OK",
          "ping": 9,
          "status": 1,
          "time": "2025-12-30 13:59:54.916"
        },
        {
          "down_count": 0,
          "duration": 60,
          "id": 8386,
          "important": false,
          "monitor_id": 1,
          "msg": "200 - OK",
          "ping": 12,
          "status": 1,
          "time": "2025-12-30 14:00:54.939"
        },
        {
          "down_count": 0,
          "duration": 60,
          "id": 8389,
          "important": false,
          "monitor_id": 1,
          "msg": "200 - OK",
          "ping": 13,
          "status": 1,
          "time": "2025-12-30 14:01:54.966"
        },
        {
          "down_count": 0,
          "duration": 60,
          "id": 8392,
          "important": false,
          "monitor_id": 1,
          "msg": "200 - OK",
          "ping": 12,
          "status": 1,
          "time": "2025-12-30 14:02:54.987"
        },
        {
          "down_count": 0,
          "duration": 60,
          "id": 8395,
          "important": false,
          "monitor_id": 1,
          "msg": "200 - OK",
          "ping": 15,
          "status": 1,
          "time": "2025-12-30 14:03:55.011"
        },
        {
          "down_count": 0,
          "duration": 60,
          "id": 8397,
          "important": false,
          "monitor_id": 1,
          "msg": "200 - OK",
          "ping": 14,
          "status": 1,
          "time": "2025-12-30 14:04:55.033"
        },
        {
          "down_count": 0,
          "duration": 60,
          "id": 8401,
          "important": false,
          "monitor_id": 1,
          "msg": "200 - OK",
          "ping": 22,
          "status": 1,
          "time": "2025-12-30 14:05:55.060"
        },
        {
          "down_count": 0,
          "duration": 60,
          "id": 8404,
          "important": false,
          "monitor_id": 1,
          "msg": "200 - OK",
          "ping": 19,
          "status": 1,
          "time": "2025-12-30 14:06:55.090"
        },
        {
          "down_count": 0,
          "duration": 60,
          "id": 8407,
          "important": false,
          "monitor_id": 1,
          "msg": "200 - OK",
          "ping": 19,
          "status": 1,
          "time": "2025-12-30 14:07:55.126"
        },
        {
          "down_count": 0,
          "duration": 60,
          "id": 8410,
          "important": false,
          "monitor_id": 1,
          "msg": "200 - OK",
          "ping": 16,
          "status": 1,
          "time": "2025-12-30 14:08:55.153"
        },
        {
          "down_count": 0,
          "duration": 60,
          "id": 8413,
          "important": false,
          "monitor_id": 1,
          "msg": "200 - OK",
          "ping": 8,
          "status": 1,
          "time": "2025-12-30 14:09:55.188"
        },
        {
          "down_count": 0,
          "duration": 60,
          "id": 8416,
          "important": false,
          "monitor_id": 1,
          "msg": "200 - OK",
          "ping": 35,
          "status": 1,
          "time": "2025-12-30 14:10:55.210"
        },
        {
          "down_count": 0,
          "duration": 60,
          "id": 8419,
          "important": false,
          "monitor_id": 1,
          "msg": "200 - OK",
          "ping": 9,
          "status": 1,
          "time": "2025-12-30 14:11:55.320"
        },
        {
          "down_count": 0,
          "duration": 60,
          "id": 8422,
          "important": false,
          "monitor_id": 1,
          "msg": "200 - OK",
          "ping": 9,
          "status": 1,
          "time": "2025-12-30 14:12:55.334"
        },
        {
          "down_count": 0,
          "duration": 60,
          "id": 8425,
          "important": false,
          "monitor_id": 1,
          "msg": "200 - OK",
          "ping": 9,
          "status": 1,
          "time": "2025-12-30 14:13:55.346"
        },
        {
          "down_count": 0,
          "duration": 60,
          "id": 8428,
          "important": false,
          "monitor_id": 1,
          "msg": "200 - OK",
          "ping": 9,
          "status": 1,
          "time": "2025-12-30 14:14:55.360"
        }
      ],
      "count": 100,
      "monitor": {
        "active": true,
        "id": 1,
        "name": "PoA API Health",
        "type": "MonitorType.HTTP"
      }
    },
    "2": {
      "beats": [
        {
          "down_count": 0,
          "duration": 60,
          "id": 8131,
          "important": false,
          "monitor_id": 2,
          "msg": "200 - OK",
          "ping": 11,
          "status": 1,
          "time": "2025-12-30 12:35:52.995"
        },
        {
          "down_count": 0,
          "duration": 60,
          "id": 8134,
          "important": false,
          "monitor_id": 2,
          "msg": "200 - OK",
          "ping": 12,
          "status": 1,
          "time": "2025-12-30 12:36:53.010"
        },
        {
          "down_count": 0,
          "duration": 60,
          "id": 8137,
          "important": false,
          "monitor_id": 2,
          "msg": "200 - OK",
          "ping": 8,
          "status": 1,
          "time": "2025-12-30 12:37:53.027"
        },
        {
          "down_count": 0,
          "duration": 60,
          "id": 8140,
          "important": false,
          "monitor_id": 2,
          "msg": "200 - OK",
          "ping": 10,
          "status": 1,
          "time": "2025-12-30 12:38:53.040"
        },
        {
          "down_count": 0,
          "duration": 60,
          "id": 8143,
          "important": false,
          "monitor_id": 2,
          "msg": "200 - OK",
          "ping": 10,
          "status": 1,
          "time": "2025-12-30 12:39:53.055"
        },
        {
          "down_count": 0,
          "duration": 60,
          "id": 8146,
          "important": false,
          "monitor_id": 2,
          "msg": "200 - OK",
          "ping": 10,
          "status": 1,
          "time": "2025-12-30 12:40:53.068"
        },
        {
          "down_count": 0,
          "duration": 60,
          "id": 8149,
          "important": false,
          "monitor_id": 2,
          "msg": "200 - OK",
          "ping": 12,
          "status": 1,
          "time": "2025-12-30 12:41:53.085"
        },
        {
          "down_count": 0,
          "duration": 60,
          "id": 8152,
          "important": false,
          "monitor_id": 2,
          "msg": "200 - OK",
          "ping": 8,
          "status": 1,
          "time": "2025-12-30 12:42:53.108"
        },
        {
          "down_count": 0,
          "duration": 60,
          "id": 8155,
          "important": false,
          "monitor_id": 2,
          "msg": "200 - OK",
          "ping": 12,
          "status": 1,
          "time": "2025-12-30 12:43:53.121"
        },
        {
          "down_count": 0,
          "duration": 60,
          "id": 8158,
          "important": false,
          "monitor_id": 2,
          "msg": "200 - OK",
          "ping": 12,
          "status": 1,
          "time": "2025-12-30 12:44:53.140"
        },
        {
          "down_count": 0,
          "duration": 60,
          "id": 8161,
          "important": false,
          "monitor_id": 2,
          "msg": "200 - OK",
          "ping": 10,
          "status": 1,
          "time": "2025-12-30 12:45:53.159"
        },
        {
          "down_count": 0,
          "duration": 60,
          "id": 8164,
          "important": false,
          "monitor_id": 2,
          "msg": "200 - OK",
          "ping": 11,
          "status": 1,
          "time": "2025-12-30 12:46:53.180"
        },
        {
          "down_count": 0,
          "duration": 60,
          "id": 8167,
          "important": false,
          "monitor_id": 2,
          "msg": "200 - OK",
          "ping": 14,
          "status": 1,
          "time": "2025-12-30 12:47:53.204"
        },
        {
          "down_count": 0,
          "duration": 60,
          "id": 8170,
          "important": false,
          "monitor_id": 2,
          "msg": "200 - OK",
          "ping": 9,
          "status": 1,
          "time": "2025-12-30 12:48:53.226"
        },
        {
          "down_count": 0,
          "duration": 60,
          "id": 8173,
          "important": false,
          "monitor_id": 2,
          "msg": "200 - OK",
          "ping": 15,
          "status": 1,
          "time": "2025-12-30 12:49:53.251"
        },
        {
          "down_count": 0,
          "duration": 60,
          "id": 8176,
          "important": false,
          "monitor_id": 2,
          "msg": "200 - OK",
          "ping": 18,
          "status": 1,
          "time": "2025-12-30 12:50:53.273"
        },
        {
          "down_count": 0,
          "duration": 60,
          "id": 8179,
          "important": false,
          "monitor_id": 2,
          "msg": "200 - OK",
          "ping": 38,
          "status": 1,
          "time": "2025-12-30 12:51:53.302"
        },
        {
          "down_count": 0,
          "duration": 60,
          "id": 8182,
          "important": false,
          "monitor_id": 2,
          "msg": "200 - OK",
          "ping": 11,
          "status": 1,
          "time": "2025-12-30 12:52:53.383"
        },
        {
          "down_count": 0,
          "duration": 60,
          "id": 8185,
          "important": false,
          "monitor_id": 2,
          "msg": "200 - OK",
          "ping": 12,
          "status": 1,
          "time": "2025-12-30 12:53:53.397"
        },
        {
          "down_count": 0,
          "duration": 60,
          "id": 8188,
          "important": false,
          "monitor_id": 2,
          "msg": "200 - OK",
          "ping": 8,
          "status": 1,
          "time": "2025-12-30 12:54:53.417"
        },
        {
          "down_count": 0,
          "duration": 60,
          "id": 8191,
          "important": false,
          "monitor_id": 2,
          "msg": "200 - OK",
          "ping": 10,
          "status": 1,
          "time": "2025-12-30 12:55:53.430"
        },
        {
          "down_count": 0,
          "duration": 60,
          "id": 8194,
          "important": false,
          "monitor_id": 2,
          "msg": "200 - OK",
          "ping": 11,
          "status": 1,
          "time": "2025-12-30 12:56:53.450"
        },
        {
          "down_count": 0,
          "duration": 60,
          "id": 8197,
          "important": false,
          "monitor_id": 2,
          "msg": "200 - OK",
          "ping": 12,
          "status": 1,
          "time": "2025-12-30 12:57:53.473"
        },
        {
          "down_count": 0,
          "duration": 60,
          "id": 8200,
          "important": false,
          "monitor_id": 2,
          "msg": "200 - OK",
          "ping": 14,
          "status": 1,
          "time": "2025-12-30 12:58:53.495"
        },
        {
          "down_count": 0,
          "duration": 60,
          "id": 8203,
          "important": false,
          "monitor_id": 2,
          "msg": "200 - OK",
          "ping": 11,
          "status": 1,
          "time": "2025-12-30 12:59:53.520"
        },
        {
          "down_count": 0,
          "duration": 60,
          "id": 8206,
          "important": false,
          "monitor_id": 2,
          "msg": "200 - OK",
          "ping": 10,
          "status": 1,
          "time": "2025-12-30 13:00:53.544"
        },
        {
          "down_count": 0,
          "duration": 60,
          "id": 8209,
          "important": false,
          "monitor_id": 2,
          "msg": "200 - OK",
          "ping": 10,
          "status": 1,
          "time": "2025-12-30 13:01:53.558"
        },
        {
          "down_count": 0,
          "duration": 60,
          "id": 8212,
          "important": false,
          "monitor_id": 2,
          "msg": "200 - OK",
          "ping": 12,
          "status": 1,
          "time": "2025-12-30 13:02:53.573"
        },
        {
          "down_count": 0,
          "duration": 60,
          "id": 8215,
          "important": false,
          "monitor_id": 2,
          "msg": "200 - OK",
          "ping": 10,
          "status": 1,
          "time": "2025-12-30 13:03:53.593"
        },
        {
          "down_count": 0,
          "duration": 60,
          "id": 8218,
          "important": false,
          "monitor_id": 2,
          "msg": "200 - OK",
          "ping": 10,
          "status": 1,
          "time": "2025-12-30 13:04:53.608"
        },
        {
          "down_count": 0,
          "duration": 60,
          "id": 8221,
          "important": false,
          "monitor_id": 2,
          "msg": "200 - OK",
          "ping": 9,
          "status": 1,
          "time": "2025-12-30 13:05:53.627"
        },
        {
          "down_count": 0,
          "duration": 60,
          "id": 8224,
          "important": false,
          "monitor_id": 2,
          "msg": "200 - OK",
          "ping": 10,
          "status": 1,
          "time": "2025-12-30 13:06:53.641"
        },
        {
          "down_count": 0,
          "duration": 60,
          "id": 8227,
          "important": false,
          "monitor_id": 2,
          "msg": "200 - OK",
          "ping": 8,
          "status": 1,
          "time": "2025-12-30 13:07:53.659"
        },
        {
          "down_count": 0,
          "duration": 60,
          "id": 8230,
          "important": false,
          "monitor_id": 2,
          "msg": "200 - OK",
          "ping": 9,
          "status": 1,
          "time": "2025-12-30 13:08:53.673"
        },
        {
          "down_count": 0,
          "duration": 60,
          "id": 8233,
          "important": false,
          "monitor_id": 2,
          "msg": "200 - OK",
          "ping": 99,
          "status": 1,
          "time": "2025-12-30 13:09:53.689"
        },
        {
          "down_count": 0,
          "duration": 60,
          "id": 8236,
          "important": false,
          "monitor_id": 2,
          "msg": "200 - OK",
          "ping": 16,
          "status": 1,
          "time": "2025-12-30 13:10:53.797"
        },
        {
          "down_count": 0,
          "duration": 60,
          "id": 8239,
          "important": false,
          "monitor_id": 2,
          "msg": "200 - OK",
          "ping": 79,
          "status": 1,
          "time": "2025-12-30 13:11:53.831"
        },
        {
          "down_count": 0,
          "duration": 60,
          "id": 8242,
          "important": false,
          "monitor_id": 2,
          "msg": "200 - OK",
          "ping": 11,
          "status": 1,
          "time": "2025-12-30 13:12:53.948"
        },
        {
          "down_count": 0,
          "duration": 60,
          "id": 8245,
          "important": false,
          "monitor_id": 2,
          "msg": "200 - OK",
          "ping": 10,
          "status": 1,
          "time": "2025-12-30 13:13:53.966"
        },
        {
          "down_count": 0,
          "duration": 60,
          "id": 8248,
          "important": false,
          "monitor_id": 2,
          "msg": "200 - OK",
          "ping": 9,
          "status": 1,
          "time": "2025-12-30 13:14:53.983"
        },
        {
          "down_count": 0,
          "duration": 60,
          "id": 8251,
          "important": false,
          "monitor_id": 2,
          "msg": "200 - OK",
          "ping": 12,
          "status": 1,
          "time": "2025-12-30 13:15:53.998"
        },
        {
          "down_count": 0,
          "duration": 60,
          "id": 8254,
          "important": false,
          "monitor_id": 2,
          "msg": "200 - OK",
          "ping": 12,
          "status": 1,
          "time": "2025-12-30 13:16:54.020"
        },
        {
          "down_count": 0,
          "duration": 60,
          "id": 8257,
          "important": false,
          "monitor_id": 2,
          "msg": "200 - OK",
          "ping": 11,
          "status": 1,
          "time": "2025-12-30 13:17:54.044"
        },
        {
          "down_count": 0,
          "duration": 60,
          "id": 8260,
          "important": false,
          "monitor_id": 2,
          "msg": "200 - OK",
          "ping": 9,
          "status": 1,
          "time": "2025-12-30 13:18:54.067"
        },
        {
          "down_count": 0,
          "duration": 60,
          "id": 8263,
          "important": false,
          "monitor_id": 2,
          "msg": "200 - OK",
          "ping": 14,
          "status": 1,
          "time": "2025-12-30 13:19:54.093"
        },
        {
          "down_count": 0,
          "duration": 60,
          "id": 8266,
          "important": false,
          "monitor_id": 2,
          "msg": "200 - OK",
          "ping": 17,
          "status": 1,
          "time": "2025-12-30 13:20:54.122"
        },
        {
          "down_count": 0,
          "duration": 60,
          "id": 8269,
          "important": false,
          "monitor_id": 2,
          "msg": "200 - OK",
          "ping": 21,
          "status": 1,
          "time": "2025-12-30 13:21:54.151"
        },
        {
          "down_count": 0,
          "duration": 60,
          "id": 8272,
          "important": false,
          "monitor_id": 2,
          "msg": "200 - OK",
          "ping": 16,
          "status": 1,
          "time": "2025-12-30 13:22:54.184"
        },
        {
          "down_count": 0,
          "duration": 60,
          "id": 8275,
          "important": false,
          "monitor_id": 2,
          "msg": "200 - OK",
          "ping": 19,
          "status": 1,
          "time": "2025-12-30 13:23:54.215"
        },
        {
          "down_count": 0,
          "duration": 60,
          "id": 8278,
          "important": false,
          "monitor_id": 2,
          "msg": "200 - OK",
          "ping": 16,
          "status": 1,
          "time": "2025-12-30 13:24:54.248"
        },
        {
          "down_count": 0,
          "duration": 60,
          "id": 8280,
          "important": false,
          "monitor_id": 2,
          "msg": "200 - OK",
          "ping": 17,
          "status": 1,
          "time": "2025-12-30 13:25:54.271"
        },
        {
          "down_count": 0,
          "duration": 60,
          "id": 8283,
          "important": false,
          "monitor_id": 2,
          "msg": "200 - OK",
          "ping": 17,
          "status": 1,
          "time": "2025-12-30 13:26:54.305"
        },
        {
          "down_count": 0,
          "duration": 60,
          "id": 8286,
          "important": false,
          "monitor_id": 2,
          "msg": "200 - OK",
          "ping": 15,
          "status": 1,
          "time": "2025-12-30 13:27:54.332"
        },
        {
          "down_count": 0,
          "duration": 60,
          "id": 8289,
          "important": false,
          "monitor_id": 2,
          "msg": "200 - OK",
          "ping": 17,
          "status": 1,
          "time": "2025-12-30 13:28:54.353"
        },
        {
          "down_count": 0,
          "duration": 60,
          "id": 8292,
          "important": false,
          "monitor_id": 2,
          "msg": "200 - OK",
          "ping": 12,
          "status": 1,
          "time": "2025-12-30 13:29:54.375"
        },
        {
          "down_count": 0,
          "duration": 60,
          "id": 8295,
          "important": false,
          "monitor_id": 2,
          "msg": "200 - OK",
          "ping": 12,
          "status": 1,
          "time": "2025-12-30 13:30:54.392"
        },
        {
          "down_count": 0,
          "duration": 60,
          "id": 8298,
          "important": false,
          "monitor_id": 2,
          "msg": "200 - OK",
          "ping": 12,
          "status": 1,
          "time": "2025-12-30 13:31:54.409"
        },
        {
          "down_count": 0,
          "duration": 60,
          "id": 8301,
          "important": false,
          "monitor_id": 2,
          "msg": "200 - OK",
          "ping": 12,
          "status": 1,
          "time": "2025-12-30 13:32:54.424"
        },
        {
          "down_count": 0,
          "duration": 60,
          "id": 8304,
          "important": false,
          "monitor_id": 2,
          "msg": "200 - OK",
          "ping": 13,
          "status": 1,
          "time": "2025-12-30 13:33:54.440"
        },
        {
          "down_count": 0,
          "duration": 60,
          "id": 8307,
          "important": false,
          "monitor_id": 2,
          "msg": "200 - OK",
          "ping": 17,
          "status": 1,
          "time": "2025-12-30 13:34:54.457"
        },
        {
          "down_count": 0,
          "duration": 60,
          "id": 8310,
          "important": false,
          "monitor_id": 2,
          "msg": "200 - OK",
          "ping": 13,
          "status": 1,
          "time": "2025-12-30 13:35:54.479"
        },
        {
          "down_count": 0,
          "duration": 60,
          "id": 8313,
          "important": false,
          "monitor_id": 2,
          "msg": "200 - OK",
          "ping": 12,
          "status": 1,
          "time": "2025-12-30 13:36:54.497"
        },
        {
          "down_count": 0,
          "duration": 60,
          "id": 8316,
          "important": false,
          "monitor_id": 2,
          "msg": "200 - OK",
          "ping": 12,
          "status": 1,
          "time": "2025-12-30 13:37:54.512"
        },
        {
          "down_count": 0,
          "duration": 60,
          "id": 8319,
          "important": false,
          "monitor_id": 2,
          "msg": "200 - OK",
          "ping": 11,
          "status": 1,
          "time": "2025-12-30 13:38:54.527"
        },
        {
          "down_count": 0,
          "duration": 60,
          "id": 8322,
          "important": false,
          "monitor_id": 2,
          "msg": "200 - OK",
          "ping": 14,
          "status": 1,
          "time": "2025-12-30 13:39:54.542"
        },
        {
          "down_count": 0,
          "duration": 60,
          "id": 8325,
          "important": false,
          "monitor_id": 2,
          "msg": "200 - OK",
          "ping": 11,
          "status": 1,
          "time": "2025-12-30 13:40:54.560"
        },
        {
          "down_count": 0,
          "duration": 60,
          "id": 8328,
          "important": false,
          "monitor_id": 2,
          "msg": "200 - OK",
          "ping": 16,
          "status": 1,
          "time": "2025-12-30 13:41:54.578"
        },
        {
          "down_count": 0,
          "duration": 60,
          "id": 8331,
          "important": false,
          "monitor_id": 2,
          "msg": "200 - OK",
          "ping": 12,
          "status": 1,
          "time": "2025-12-30 13:42:54.598"
        },
        {
          "down_count": 0,
          "duration": 60,
          "id": 8334,
          "important": false,
          "monitor_id": 2,
          "msg": "200 - OK",
          "ping": 14,
          "status": 1,
          "time": "2025-12-30 13:43:54.614"
        },
        {
          "down_count": 0,
          "duration": 60,
          "id": 8337,
          "important": false,
          "monitor_id": 2,
          "msg": "200 - OK",
          "ping": 11,
          "status": 1,
          "time": "2025-12-30 13:44:54.633"
        },
        {
          "down_count": 0,
          "duration": 60,
          "id": 8340,
          "important": false,
          "monitor_id": 2,
          "msg": "200 - OK",
          "ping": 11,
          "status": 1,
          "time": "2025-12-30 13:45:54.648"
        },
        {
          "down_count": 0,
          "duration": 60,
          "id": 8343,
          "important": false,
          "monitor_id": 2,
          "msg": "200 - OK",
          "ping": 11,
          "status": 1,
          "time": "2025-12-30 13:46:54.665"
        },
        {
          "down_count": 0,
          "duration": 60,
          "id": 8346,
          "important": false,
          "monitor_id": 2,
          "msg": "200 - OK",
          "ping": 15,
          "status": 1,
          "time": "2025-12-30 13:47:54.682"
        },
        {
          "down_count": 0,
          "duration": 60,
          "id": 8349,
          "important": false,
          "monitor_id": 2,
          "msg": "200 - OK",
          "ping": 12,
          "status": 1,
          "time": "2025-12-30 13:48:54.702"
        },
        {
          "down_count": 0,
          "duration": 60,
          "id": 8352,
          "important": false,
          "monitor_id": 2,
          "msg": "200 - OK",
          "ping": 14,
          "status": 1,
          "time": "2025-12-30 13:49:54.718"
        },
        {
          "down_count": 0,
          "duration": 60,
          "id": 8355,
          "important": false,
          "monitor_id": 2,
          "msg": "200 - OK",
          "ping": 10,
          "status": 1,
          "time": "2025-12-30 13:50:54.736"
        },
        {
          "down_count": 0,
          "duration": 60,
          "id": 8358,
          "important": false,
          "monitor_id": 2,
          "msg": "200 - OK",
          "ping": 13,
          "status": 1,
          "time": "2025-12-30 13:51:54.753"
        },
        {
          "down_count": 0,
          "duration": 60,
          "id": 8361,
          "important": false,
          "monitor_id": 2,
          "msg": "200 - OK",
          "ping": 13,
          "status": 1,
          "time": "2025-12-30 13:52:54.770"
        },
        {
          "down_count": 0,
          "duration": 60,
          "id": 8364,
          "important": false,
          "monitor_id": 2,
          "msg": "200 - OK",
          "ping": 11,
          "status": 1,
          "time": "2025-12-30 13:53:54.786"
        },
        {
          "down_count": 0,
          "duration": 60,
          "id": 8367,
          "important": false,
          "monitor_id": 2,
          "msg": "200 - OK",
          "ping": 10,
          "status": 1,
          "time": "2025-12-30 13:54:54.802"
        },
        {
          "down_count": 0,
          "duration": 60,
          "id": 8370,
          "important": false,
          "monitor_id": 2,
          "msg": "200 - OK",
          "ping": 15,
          "status": 1,
          "time": "2025-12-30 13:55:54.815"
        },
        {
          "down_count": 0,
          "duration": 60,
          "id": 8373,
          "important": false,
          "monitor_id": 2,
          "msg": "200 - OK",
          "ping": 13,
          "status": 1,
          "time": "2025-12-30 13:56:54.835"
        },
        {
          "down_count": 0,
          "duration": 60,
          "id": 8376,
          "important": false,
          "monitor_id": 2,
          "msg": "200 - OK",
          "ping": 21,
          "status": 1,
          "time": "2025-12-30 13:57:54.853"
        },
        {
          "down_count": 0,
          "duration": 60,
          "id": 8379,
          "important": false,
          "monitor_id": 2,
          "msg": "200 - OK",
          "ping": 13,
          "status": 1,
          "time": "2025-12-30 13:58:54.880"
        },
        {
          "down_count": 0,
          "duration": 60,
          "id": 8382,
          "important": false,
          "monitor_id": 2,
          "msg": "200 - OK",
          "ping": 17,
          "status": 1,
          "time": "2025-12-30 13:59:54.899"
        },
        {
          "down_count": 0,
          "duration": 60,
          "id": 8385,
          "important": false,
          "monitor_id": 2,
          "msg": "200 - OK",
          "ping": 18,
          "status": 1,
          "time": "2025-12-30 14:00:54.926"
        },
        {
          "down_count": 0,
          "duration": 60,
          "id": 8388,
          "important": false,
          "monitor_id": 2,
          "msg": "200 - OK",
          "ping": 15,
          "status": 1,
          "time": "2025-12-30 14:01:54.956"
        },
        {
          "down_count": 0,
          "duration": 60,
          "id": 8391,
          "important": false,
          "monitor_id": 2,
          "msg": "200 - OK",
          "ping": 18,
          "status": 1,
          "time": "2025-12-30 14:02:54.975"
        },
        {
          "down_count": 0,
          "duration": 60,
          "id": 8394,
          "important": false,
          "monitor_id": 2,
          "msg": "200 - OK",
          "ping": 20,
          "status": 1,
          "time": "2025-12-30 14:03:55.003"
        },
        {
          "down_count": 0,
          "duration": 60,
          "id": 8398,
          "important": false,
          "monitor_id": 2,
          "msg": "200 - OK",
          "ping": 21,
          "status": 1,
          "time": "2025-12-30 14:04:55.033"
        },
        {
          "down_count": 0,
          "duration": 60,
          "id": 8400,
          "important": false,
          "monitor_id": 2,
          "msg": "200 - OK",
          "ping": 17,
          "status": 1,
          "time": "2025-12-30 14:05:55.061"
        },
        {
          "down_count": 0,
          "duration": 60,
          "id": 8403,
          "important": false,
          "monitor_id": 2,
          "msg": "200 - OK",
          "ping": 23,
          "status": 1,
          "time": "2025-12-30 14:06:55.089"
        },
        {
          "down_count": 0,
          "duration": 60,
          "id": 8406,
          "important": false,
          "monitor_id": 2,
          "msg": "200 - OK",
          "ping": 19,
          "status": 1,
          "time": "2025-12-30 14:07:55.122"
        },
        {
          "down_count": 0,
          "duration": 60,
          "id": 8409,
          "important": false,
          "monitor_id": 2,
          "msg": "200 - OK",
          "ping": 15,
          "status": 1,
          "time": "2025-12-30 14:08:55.149"
        },
        {
          "down_count": 0,
          "duration": 60,
          "id": 8412,
          "important": false,
          "monitor_id": 2,
          "msg": "200 - OK",
          "ping": 12,
          "status": 1,
          "time": "2025-12-30 14:09:55.179"
        },
        {
          "down_count": 0,
          "duration": 60,
          "id": 8415,
          "important": false,
          "monitor_id": 2,
          "msg": "200 - OK",
          "ping": 17,
          "status": 1,
          "time": "2025-12-30 14:10:55.197"
        },
        {
          "down_count": 0,
          "duration": 60,
          "id": 8418,
          "important": false,
          "monitor_id": 2,
          "msg": "200 - OK",
          "ping": 13,
          "status": 1,
          "time": "2025-12-30 14:11:55.253"
        },
        {
          "down_count": 0,
          "duration": 60,
          "id": 8421,
          "important": false,
          "monitor_id": 2,
          "msg": "200 - OK",
          "ping": 10,
          "status": 1,
          "time": "2025-12-30 14:12:55.270"
        },
        {
          "down_count": 0,
          "duration": 60,
          "id": 8424,
          "important": false,
          "monitor_id": 2,
          "msg": "200 - OK",
          "ping": 19,
          "status": 1,
          "time": "2025-12-30 14:13:55.284"
        },
        {
          "down_count": 0,
          "duration": 60,
          "id": 8427,
          "important": false,
          "monitor_id": 2,
          "msg": "200 - OK",
          "ping": 14,
          "status": 1,
          "time": "2025-12-30 14:14:55.307"
        }
      ],
      "count": 100,
      "monitor": {
        "active": true,
        "id": 2,
        "name": "PoA Latest",
        "type": "MonitorType.HTTP"
      }
    },
    "3": {
      "beats": [
        {
          "down_count": 0,
          "duration": 60,
          "id": 8132,
          "important": false,
          "monitor_id": 3,
          "msg": "200 - OK",
          "ping": 12,
          "status": 1,
          "time": "2025-12-30 12:35:53.069"
        },
        {
          "down_count": 0,
          "duration": 60,
          "id": 8135,
          "important": false,
          "monitor_id": 3,
          "msg": "200 - OK",
          "ping": 11,
          "status": 1,
          "time": "2025-12-30 12:36:53.085"
        },
        {
          "down_count": 0,
          "duration": 60,
          "id": 8138,
          "important": false,
          "monitor_id": 3,
          "msg": "200 - OK",
          "ping": 10,
          "status": 1,
          "time": "2025-12-30 12:37:53.100"
        },
        {
          "down_count": 0,
          "duration": 60,
          "id": 8141,
          "important": false,
          "monitor_id": 3,
          "msg": "200 - OK",
          "ping": 9,
          "status": 1,
          "time": "2025-12-30 12:38:53.114"
        },
        {
          "down_count": 0,
          "duration": 60,
          "id": 8144,
          "important": false,
          "monitor_id": 3,
          "msg": "200 - OK",
          "ping": 11,
          "status": 1,
          "time": "2025-12-30 12:39:53.127"
        },
        {
          "down_count": 0,
          "duration": 60,
          "id": 8147,
          "important": false,
          "monitor_id": 3,
          "msg": "200 - OK",
          "ping": 12,
          "status": 1,
          "time": "2025-12-30 12:40:53.144"
        },
        {
          "down_count": 0,
          "duration": 60,
          "id": 8150,
          "important": false,
          "monitor_id": 3,
          "msg": "200 - OK",
          "ping": 10,
          "status": 1,
          "time": "2025-12-30 12:41:53.161"
        },
        {
          "down_count": 0,
          "duration": 60,
          "id": 8153,
          "important": false,
          "monitor_id": 3,
          "msg": "200 - OK",
          "ping": 12,
          "status": 1,
          "time": "2025-12-30 12:42:53.175"
        },
        {
          "down_count": 0,
          "duration": 60,
          "id": 8156,
          "important": false,
          "monitor_id": 3,
          "msg": "200 - OK",
          "ping": 10,
          "status": 1,
          "time": "2025-12-30 12:43:53.191"
        },
        {
          "down_count": 0,
          "duration": 60,
          "id": 8159,
          "important": false,
          "monitor_id": 3,
          "msg": "200 - OK",
          "ping": 9,
          "status": 1,
          "time": "2025-12-30 12:44:53.205"
        },
        {
          "down_count": 0,
          "duration": 60,
          "id": 8162,
          "important": false,
          "monitor_id": 3,
          "msg": "200 - OK",
          "ping": 12,
          "status": 1,
          "time": "2025-12-30 12:45:53.218"
        },
        {
          "down_count": 0,
          "duration": 60,
          "id": 8165,
          "important": false,
          "monitor_id": 3,
          "msg": "200 - OK",
          "ping": 14,
          "status": 1,
          "time": "2025-12-30 12:46:53.236"
        },
        {
          "down_count": 0,
          "duration": 60,
          "id": 8168,
          "important": false,
          "monitor_id": 3,
          "msg": "200 - OK",
          "ping": 20,
          "status": 1,
          "time": "2025-12-30 12:47:53.253"
        },
        {
          "down_count": 0,
          "duration": 60,
          "id": 8171,
          "important": false,
          "monitor_id": 3,
          "msg": "200 - OK",
          "ping": 10,
          "status": 1,
          "time": "2025-12-30 12:48:53.277"
        },
        {
          "down_count": 0,
          "duration": 60,
          "id": 8174,
          "important": false,
          "monitor_id": 3,
          "msg": "200 - OK",
          "ping": 12,
          "status": 1,
          "time": "2025-12-30 12:49:53.290"
        },
        {
          "down_count": 0,
          "duration": 60,
          "id": 8177,
          "important": false,
          "monitor_id": 3,
          "msg": "200 - OK",
          "ping": 12,
          "status": 1,
          "time": "2025-12-30 12:50:53.309"
        },
        {
          "down_count": 0,
          "duration": 60,
          "id": 8180,
          "important": false,
          "monitor_id": 3,
          "msg": "200 - OK",
          "ping": 20,
          "status": 1,
          "time": "2025-12-30 12:51:53.342"
        },
        {
          "down_count": 0,
          "duration": 60,
          "id": 8183,
          "important": false,
          "monitor_id": 3,
          "msg": "200 - OK",
          "ping": 13,
          "status": 1,
          "time": "2025-12-30 12:52:53.420"
        },
        {
          "down_count": 0,
          "duration": 60,
          "id": 8186,
          "important": false,
          "monitor_id": 3,
          "msg": "200 - OK",
          "ping": 10,
          "status": 1,
          "time": "2025-12-30 12:53:53.437"
        },
        {
          "down_count": 0,
          "duration": 60,
          "id": 8189,
          "important": false,
          "monitor_id": 3,
          "msg": "200 - OK",
          "ping": 10,
          "status": 1,
          "time": "2025-12-30 12:54:53.452"
        },
        {
          "down_count": 0,
          "duration": 60,
          "id": 8192,
          "important": false,
          "monitor_id": 3,
          "msg": "200 - OK",
          "ping": 11,
          "status": 1,
          "time": "2025-12-30 12:55:53.466"
        },
        {
          "down_count": 0,
          "duration": 60,
          "id": 8195,
          "important": false,
          "monitor_id": 3,
          "msg": "200 - OK",
          "ping": 10,
          "status": 1,
          "time": "2025-12-30 12:56:53.482"
        },
        {
          "down_count": 0,
          "duration": 60,
          "id": 8198,
          "important": false,
          "monitor_id": 3,
          "msg": "200 - OK",
          "ping": 10,
          "status": 1,
          "time": "2025-12-30 12:57:53.497"
        },
        {
          "down_count": 0,
          "duration": 60,
          "id": 8201,
          "important": false,
          "monitor_id": 3,
          "msg": "200 - OK",
          "ping": 10,
          "status": 1,
          "time": "2025-12-30 12:58:53.511"
        },
        {
          "down_count": 0,
          "duration": 60,
          "id": 8204,
          "important": false,
          "monitor_id": 3,
          "msg": "200 - OK",
          "ping": 13,
          "status": 1,
          "time": "2025-12-30 12:59:53.537"
        },
        {
          "down_count": 0,
          "duration": 60,
          "id": 8207,
          "important": false,
          "monitor_id": 3,
          "msg": "200 - OK",
          "ping": 9,
          "status": 1,
          "time": "2025-12-30 13:00:53.562"
        },
        {
          "down_count": 0,
          "duration": 60,
          "id": 8210,
          "important": false,
          "monitor_id": 3,
          "msg": "200 - OK",
          "ping": 10,
          "status": 1,
          "time": "2025-12-30 13:01:53.574"
        },
        {
          "down_count": 0,
          "duration": 60,
          "id": 8213,
          "important": false,
          "monitor_id": 3,
          "msg": "200 - OK",
          "ping": 11,
          "status": 1,
          "time": "2025-12-30 13:02:53.591"
        },
        {
          "down_count": 0,
          "duration": 60,
          "id": 8216,
          "important": false,
          "monitor_id": 3,
          "msg": "200 - OK",
          "ping": 11,
          "status": 1,
          "time": "2025-12-30 13:03:53.612"
        },
        {
          "down_count": 0,
          "duration": 60,
          "id": 8219,
          "important": false,
          "monitor_id": 3,
          "msg": "200 - OK",
          "ping": 10,
          "status": 1,
          "time": "2025-12-30 13:04:53.626"
        },
        {
          "down_count": 0,
          "duration": 60,
          "id": 8222,
          "important": false,
          "monitor_id": 3,
          "msg": "200 - OK",
          "ping": 10,
          "status": 1,
          "time": "2025-12-30 13:05:53.642"
        },
        {
          "down_count": 0,
          "duration": 60,
          "id": 8225,
          "important": false,
          "monitor_id": 3,
          "msg": "200 - OK",
          "ping": 14,
          "status": 1,
          "time": "2025-12-30 13:06:53.658"
        },
        {
          "down_count": 0,
          "duration": 60,
          "id": 8228,
          "important": false,
          "monitor_id": 3,
          "msg": "200 - OK",
          "ping": 9,
          "status": 1,
          "time": "2025-12-30 13:07:53.679"
        },
        {
          "down_count": 0,
          "duration": 60,
          "id": 8231,
          "important": false,
          "monitor_id": 3,
          "msg": "200 - OK",
          "ping": 11,
          "status": 1,
          "time": "2025-12-30 13:08:53.693"
        },
        {
          "down_count": 0,
          "duration": 60,
          "id": 8234,
          "important": false,
          "monitor_id": 3,
          "msg": "200 - OK",
          "ping": 83,
          "status": 1,
          "time": "2025-12-30 13:09:53.706"
        },
        {
          "down_count": 0,
          "duration": 60,
          "id": 8237,
          "important": false,
          "monitor_id": 3,
          "msg": "200 - OK",
          "ping": 11,
          "status": 1,
          "time": "2025-12-30 13:10:53.798"
        },
        {
          "down_count": 0,
          "duration": 60,
          "id": 8240,
          "important": false,
          "monitor_id": 3,
          "msg": "200 - OK",
          "ping": 15,
          "status": 1,
          "time": "2025-12-30 13:11:53.845"
        },
        {
          "down_count": 0,
          "duration": 60,
          "id": 8243,
          "important": false,
          "monitor_id": 3,
          "msg": "200 - OK",
          "ping": 12,
          "status": 1,
          "time": "2025-12-30 13:12:53.960"
        },
        {
          "down_count": 0,
          "duration": 60,
          "id": 8246,
          "important": false,
          "monitor_id": 3,
          "msg": "200 - OK",
          "ping": 9,
          "status": 1,
          "time": "2025-12-30 13:13:53.980"
        },
        {
          "down_count": 0,
          "duration": 60,
          "id": 8249,
          "important": false,
          "monitor_id": 3,
          "msg": "200 - OK",
          "ping": 11,
          "status": 1,
          "time": "2025-12-30 13:14:53.996"
        },
        {
          "down_count": 0,
          "duration": 60,
          "id": 8252,
          "important": false,
          "monitor_id": 3,
          "msg": "200 - OK",
          "ping": 14,
          "status": 1,
          "time": "2025-12-30 13:15:54.016"
        },
        {
          "down_count": 0,
          "duration": 60,
          "id": 8255,
          "important": false,
          "monitor_id": 3,
          "msg": "200 - OK",
          "ping": 9,
          "status": 1,
          "time": "2025-12-30 13:16:54.040"
        },
        {
          "down_count": 0,
          "duration": 60,
          "id": 8258,
          "important": false,
          "monitor_id": 3,
          "msg": "200 - OK",
          "ping": 10,
          "status": 1,
          "time": "2025-12-30 13:17:54.058"
        },
        {
          "down_count": 0,
          "duration": 60,
          "id": 8261,
          "important": false,
          "monitor_id": 3,
          "msg": "200 - OK",
          "ping": 9,
          "status": 1,
          "time": "2025-12-30 13:18:54.079"
        },
        {
          "down_count": 0,
          "duration": 60,
          "id": 8264,
          "important": false,
          "monitor_id": 3,
          "msg": "200 - OK",
          "ping": 14,
          "status": 1,
          "time": "2025-12-30 13:19:54.100"
        },
        {
          "down_count": 0,
          "duration": 60,
          "id": 8267,
          "important": false,
          "monitor_id": 3,
          "msg": "200 - OK",
          "ping": 13,
          "status": 1,
          "time": "2025-12-30 13:20:54.139"
        },
        {
          "down_count": 0,
          "duration": 60,
          "id": 8270,
          "important": false,
          "monitor_id": 3,
          "msg": "200 - OK",
          "ping": 15,
          "status": 1,
          "time": "2025-12-30 13:21:54.174"
        },
        {
          "down_count": 0,
          "duration": 60,
          "id": 8273,
          "important": false,
          "monitor_id": 3,
          "msg": "200 - OK",
          "ping": 12,
          "status": 1,
          "time": "2025-12-30 13:22:54.204"
        },
        {
          "down_count": 0,
          "duration": 60,
          "id": 8276,
          "important": false,
          "monitor_id": 3,
          "msg": "200 - OK",
          "ping": 11,
          "status": 1,
          "time": "2025-12-30 13:23:54.235"
        },
        {
          "down_count": 0,
          "duration": 60,
          "id": 8279,
          "important": false,
          "monitor_id": 3,
          "msg": "200 - OK",
          "ping": 10,
          "status": 1,
          "time": "2025-12-30 13:24:54.266"
        },
        {
          "down_count": 0,
          "duration": 60,
          "id": 8282,
          "important": false,
          "monitor_id": 3,
          "msg": "200 - OK",
          "ping": 15,
          "status": 1,
          "time": "2025-12-30 13:25:54.291"
        },
        {
          "down_count": 0,
          "duration": 60,
          "id": 8285,
          "important": false,
          "monitor_id": 3,
          "msg": "200 - OK",
          "ping": 12,
          "status": 1,
          "time": "2025-12-30 13:26:54.331"
        },
        {
          "down_count": 0,
          "duration": 60,
          "id": 8288,
          "important": false,
          "monitor_id": 3,
          "msg": "200 - OK",
          "ping": 11,
          "status": 1,
          "time": "2025-12-30 13:27:54.361"
        },
        {
          "down_count": 0,
          "duration": 60,
          "id": 8291,
          "important": false,
          "monitor_id": 3,
          "msg": "200 - OK",
          "ping": 12,
          "status": 1,
          "time": "2025-12-30 13:28:54.383"
        },
        {
          "down_count": 0,
          "duration": 60,
          "id": 8294,
          "important": false,
          "monitor_id": 3,
          "msg": "200 - OK",
          "ping": 10,
          "status": 1,
          "time": "2025-12-30 13:29:54.405"
        },
        {
          "down_count": 0,
          "duration": 60,
          "id": 8297,
          "important": false,
          "monitor_id": 3,
          "msg": "200 - OK",
          "ping": 43,
          "status": 1,
          "time": "2025-12-30 13:30:54.425"
        },
        {
          "down_count": 0,
          "duration": 60,
          "id": 8300,
          "important": false,
          "monitor_id": 3,
          "msg": "200 - OK",
          "ping": 10,
          "status": 1,
          "time": "2025-12-30 13:31:54.489"
        },
        {
          "down_count": 0,
          "duration": 60,
          "id": 8303,
          "important": false,
          "monitor_id": 3,
          "msg": "200 - OK",
          "ping": 10,
          "status": 1,
          "time": "2025-12-30 13:32:54.503"
        },
        {
          "down_count": 0,
          "duration": 60,
          "id": 8306,
          "important": false,
          "monitor_id": 3,
          "msg": "200 - OK",
          "ping": 10,
          "status": 1,
          "time": "2025-12-30 13:33:54.519"
        },
        {
          "down_count": 0,
          "duration": 60,
          "id": 8309,
          "important": false,
          "monitor_id": 3,
          "msg": "200 - OK",
          "ping": 12,
          "status": 1,
          "time": "2025-12-30 13:34:54.535"
        },
        {
          "down_count": 0,
          "duration": 60,
          "id": 8312,
          "important": false,
          "monitor_id": 3,
          "msg": "200 - OK",
          "ping": 12,
          "status": 1,
          "time": "2025-12-30 13:35:54.551"
        },
        {
          "down_count": 0,
          "duration": 60,
          "id": 8315,
          "important": false,
          "monitor_id": 3,
          "msg": "200 - OK",
          "ping": 11,
          "status": 1,
          "time": "2025-12-30 13:36:54.567"
        },
        {
          "down_count": 0,
          "duration": 60,
          "id": 8318,
          "important": false,
          "monitor_id": 3,
          "msg": "200 - OK",
          "ping": 10,
          "status": 1,
          "time": "2025-12-30 13:37:54.583"
        },
        {
          "down_count": 0,
          "duration": 60,
          "id": 8321,
          "important": false,
          "monitor_id": 3,
          "msg": "200 - OK",
          "ping": 10,
          "status": 1,
          "time": "2025-12-30 13:38:54.595"
        },
        {
          "down_count": 0,
          "duration": 60,
          "id": 8324,
          "important": false,
          "monitor_id": 3,
          "msg": "200 - OK",
          "ping": 11,
          "status": 1,
          "time": "2025-12-30 13:39:54.608"
        },
        {
          "down_count": 0,
          "duration": 60,
          "id": 8327,
          "important": false,
          "monitor_id": 3,
          "msg": "200 - OK",
          "ping": 10,
          "status": 1,
          "time": "2025-12-30 13:40:54.624"
        },
        {
          "down_count": 0,
          "duration": 60,
          "id": 8330,
          "important": false,
          "monitor_id": 3,
          "msg": "200 - OK",
          "ping": 13,
          "status": 1,
          "time": "2025-12-30 13:41:54.638"
        },
        {
          "down_count": 0,
          "duration": 60,
          "id": 8333,
          "important": false,
          "monitor_id": 3,
          "msg": "200 - OK",
          "ping": 12,
          "status": 1,
          "time": "2025-12-30 13:42:54.655"
        },
        {
          "down_count": 0,
          "duration": 60,
          "id": 8336,
          "important": false,
          "monitor_id": 3,
          "msg": "200 - OK",
          "ping": 10,
          "status": 1,
          "time": "2025-12-30 13:43:54.671"
        },
        {
          "down_count": 0,
          "duration": 60,
          "id": 8339,
          "important": false,
          "monitor_id": 3,
          "msg": "200 - OK",
          "ping": 9,
          "status": 1,
          "time": "2025-12-30 13:44:54.684"
        },
        {
          "down_count": 0,
          "duration": 60,
          "id": 8342,
          "important": false,
          "monitor_id": 3,
          "msg": "200 - OK",
          "ping": 13,
          "status": 1,
          "time": "2025-12-30 13:45:54.696"
        },
        {
          "down_count": 0,
          "duration": 60,
          "id": 8345,
          "important": false,
          "monitor_id": 3,
          "msg": "200 - OK",
          "ping": 9,
          "status": 1,
          "time": "2025-12-30 13:46:54.712"
        },
        {
          "down_count": 0,
          "duration": 60,
          "id": 8348,
          "important": false,
          "monitor_id": 3,
          "msg": "200 - OK",
          "ping": 11,
          "status": 1,
          "time": "2025-12-30 13:47:54.725"
        },
        {
          "down_count": 0,
          "duration": 60,
          "id": 8351,
          "important": false,
          "monitor_id": 3,
          "msg": "200 - OK",
          "ping": 10,
          "status": 1,
          "time": "2025-12-30 13:48:54.738"
        },
        {
          "down_count": 0,
          "duration": 60,
          "id": 8354,
          "important": false,
          "monitor_id": 3,
          "msg": "200 - OK",
          "ping": 9,
          "status": 1,
          "time": "2025-12-30 13:49:54.755"
        },
        {
          "down_count": 0,
          "duration": 60,
          "id": 8357,
          "important": false,
          "monitor_id": 3,
          "msg": "200 - OK",
          "ping": 42,
          "status": 1,
          "time": "2025-12-30 13:50:54.767"
        },
        {
          "down_count": 0,
          "duration": 60,
          "id": 8360,
          "important": false,
          "monitor_id": 3,
          "msg": "200 - OK",
          "ping": 9,
          "status": 1,
          "time": "2025-12-30 13:51:54.841"
        },
        {
          "down_count": 0,
          "duration": 60,
          "id": 8363,
          "important": false,
          "monitor_id": 3,
          "msg": "200 - OK",
          "ping": 12,
          "status": 1,
          "time": "2025-12-30 13:52:54.853"
        },
        {
          "down_count": 0,
          "duration": 60,
          "id": 8366,
          "important": false,
          "monitor_id": 3,
          "msg": "200 - OK",
          "ping": 11,
          "status": 1,
          "time": "2025-12-30 13:53:54.870"
        },
        {
          "down_count": 0,
          "duration": 60,
          "id": 8369,
          "important": false,
          "monitor_id": 3,
          "msg": "200 - OK",
          "ping": 10,
          "status": 1,
          "time": "2025-12-30 13:54:54.884"
        },
        {
          "down_count": 0,
          "duration": 60,
          "id": 8372,
          "important": false,
          "monitor_id": 3,
          "msg": "200 - OK",
          "ping": 10,
          "status": 1,
          "time": "2025-12-30 13:55:54.897"
        },
        {
          "down_count": 0,
          "duration": 60,
          "id": 8375,
          "important": false,
          "monitor_id": 3,
          "msg": "200 - OK",
          "ping": 11,
          "status": 1,
          "time": "2025-12-30 13:56:54.911"
        },
        {
          "down_count": 0,
          "duration": 60,
          "id": 8378,
          "important": false,
          "monitor_id": 3,
          "msg": "200 - OK",
          "ping": 13,
          "status": 1,
          "time": "2025-12-30 13:57:54.927"
        },
        {
          "down_count": 0,
          "duration": 60,
          "id": 8381,
          "important": false,
          "monitor_id": 3,
          "msg": "200 - OK",
          "ping": 10,
          "status": 1,
          "time": "2025-12-30 13:58:54.946"
        },
        {
          "down_count": 0,
          "duration": 60,
          "id": 8384,
          "important": false,
          "monitor_id": 3,
          "msg": "200 - OK",
          "ping": 10,
          "status": 1,
          "time": "2025-12-30 13:59:54.959"
        },
        {
          "down_count": 0,
          "duration": 60,
          "id": 8387,
          "important": false,
          "monitor_id": 3,
          "msg": "200 - OK",
          "ping": 11,
          "status": 1,
          "time": "2025-12-30 14:00:54.972"
        },
        {
          "down_count": 0,
          "duration": 60,
          "id": 8390,
          "important": false,
          "monitor_id": 3,
          "msg": "200 - OK",
          "ping": 11,
          "status": 1,
          "time": "2025-12-30 14:01:54.986"
        },
        {
          "down_count": 0,
          "duration": 60,
          "id": 8393,
          "important": false,
          "monitor_id": 3,
          "msg": "200 - OK",
          "ping": 12,
          "status": 1,
          "time": "2025-12-30 14:02:55.005"
        },
        {
          "down_count": 0,
          "duration": 60,
          "id": 8396,
          "important": false,
          "monitor_id": 3,
          "msg": "200 - OK",
          "ping": 10,
          "status": 1,
          "time": "2025-12-30 14:03:55.028"
        },
        {
          "down_count": 0,
          "duration": 60,
          "id": 8399,
          "important": false,
          "monitor_id": 3,
          "msg": "200 - OK",
          "ping": 10,
          "status": 1,
          "time": "2025-12-30 14:04:55.052"
        },
        {
          "down_count": 0,
          "duration": 60,
          "id": 8402,
          "important": false,
          "monitor_id": 3,
          "msg": "200 - OK",
          "ping": 12,
          "status": 1,
          "time": "2025-12-30 14:05:55.079"
        },
        {
          "down_count": 0,
          "duration": 60,
          "id": 8405,
          "important": false,
          "monitor_id": 3,
          "msg": "200 - OK",
          "ping": 14,
          "status": 1,
          "time": "2025-12-30 14:06:55.108"
        },
        {
          "down_count": 0,
          "duration": 60,
          "id": 8408,
          "important": false,
          "monitor_id": 3,
          "msg": "200 - OK",
          "ping": 14,
          "status": 1,
          "time": "2025-12-30 14:07:55.144"
        },
        {
          "down_count": 0,
          "duration": 60,
          "id": 8411,
          "important": false,
          "monitor_id": 3,
          "msg": "200 - OK",
          "ping": 12,
          "status": 1,
          "time": "2025-12-30 14:08:55.177"
        },
        {
          "down_count": 0,
          "duration": 60,
          "id": 8414,
          "important": false,
          "monitor_id": 3,
          "msg": "200 - OK",
          "ping": 11,
          "status": 1,
          "time": "2025-12-30 14:09:55.206"
        },
        {
          "down_count": 0,
          "duration": 60,
          "id": 8417,
          "important": false,
          "monitor_id": 3,
          "msg": "200 - OK",
          "ping": 40,
          "status": 1,
          "time": "2025-12-30 14:10:55.224"
        },
        {
          "down_count": 0,
          "duration": 60,
          "id": 8420,
          "important": false,
          "monitor_id": 3,
          "msg": "200 - OK",
          "ping": 12,
          "status": 1,
          "time": "2025-12-30 14:11:55.328"
        },
        {
          "down_count": 0,
          "duration": 60,
          "id": 8423,
          "important": false,
          "monitor_id": 3,
          "msg": "200 - OK",
          "ping": 10,
          "status": 1,
          "time": "2025-12-30 14:12:55.348"
        },
        {
          "down_count": 0,
          "duration": 60,
          "id": 8426,
          "important": false,
          "monitor_id": 3,
          "msg": "200 - OK",
          "ping": 10,
          "status": 1,
          "time": "2025-12-30 14:13:55.365"
        },
        {
          "down_count": 0,
          "duration": 60,
          "id": 8429,
          "important": false,
          "monitor_id": 3,
          "msg": "200 - OK",
          "ping": 14,
          "status": 1,
          "time": "2025-12-30 14:14:55.377"
        }
      ],
      "count": 100,
      "monitor": {
        "active": true,
        "id": 3,
        "name": "PoA Bundle Latest",
        "type": "MonitorType.HTTP"
      }
    }
  },
  "generated_at_utc": "2025-12-30T14:15:41.000681+00:00",
  "heartbeats_total": 300,
  "kuma_url": "http://uptime-kuma:3001",
  "monitors_count": 3
}
