{
  "generated_at_utc": "2025-12-31T11:24:49.567517+00:00",
  "kuma_url": "http://uptime-kuma:3001",
  "monitors_count": 3,
  "heartbeats_total": 300,
  "data": {
    "5": {
      "monitor": {
        "id": 5,
        "name": "PoA API Health",
        "type": "MonitorType.HTTP",
        "active": true
      },
      "count": 100,
      "beats": [
        {
          "id": 11885,
          "important": false,
          "monitor_id": 5,
          "status": 1,
          "msg": "200 - OK",
          "time": "2025-12-31 09:44:53.830",
          "ping": 12,
          "duration": 60,
          "down_count": 0
        },
        {
          "id": 11888,
          "important": false,
          "monitor_id": 5,
          "status": 1,
          "msg": "200 - OK",
          "time": "2025-12-31 09:45:53.845",
          "ping": 13,
          "duration": 60,
          "down_count": 0
        },
        {
          "id": 11891,
          "important": false,
          "monitor_id": 5,
          "status": 1,
          "msg": "200 - OK",
          "time": "2025-12-31 09:46:53.864",
          "ping": 10,
          "duration": 60,
          "down_count": 0
        },
        {
          "id": 11894,
          "important": false,
          "monitor_id": 5,
          "status": 1,
          "msg": "200 - OK",
          "time": "2025-12-31 09:47:53.877",
          "ping": 13,
          "duration": 60,
          "down_count": 0
        },
        {
          "id": 11897,
          "important": false,
          "monitor_id": 5,
          "status": 1,
          "msg": "200 - OK",
          "time": "2025-12-31 09:48:53.892",
          "ping": 13,
          "duration": 60,
          "down_count": 0
        },
        {
          "id": 11900,
          "important": false,
          "monitor_id": 5,
          "status": 1,
          "msg": "200 - OK",
          "time": "2025-12-31 09:49:53.909",
          "ping": 11,
          "duration": 60,
          "down_count": 0
        },
        {
          "id": 11903,
          "important": false,
          "monitor_id": 5,
          "status": 1,
          "msg": "200 - OK",
          "time": "2025-12-31 09:50:53.924",
          "ping": 10,
          "duration": 60,
          "down_count": 0
        },
        {
          "id": 11906,
          "important": false,
          "monitor_id": 5,
          "status": 1,
          "msg": "200 - OK",
          "time": "2025-12-31 09:51:53.936",
          "ping": 14,
          "duration": 60,
          "down_count": 0
        },
        {
          "id": 11909,
          "important": false,
          "monitor_id": 5,
          "status": 1,
          "msg": "200 - OK",
          "time": "2025-12-31 09:52:53.955",
          "ping": 13,
          "duration": 60,
          "down_count": 0
        },
        {
          "id": 11912,
          "important": false,
          "monitor_id": 5,
          "status": 1,
          "msg": "200 - OK",
          "time": "2025-12-31 09:53:53.973",
          "ping": 12,
          "duration": 60,
          "down_count": 0
        },
        {
          "id": 11915,
          "important": false,
          "monitor_id": 5,
          "status": 1,
          "msg": "200 - OK",
          "time": "2025-12-31 09:54:53.995",
          "ping": 14,
          "duration": 60,
          "down_count": 0
        },
        {
          "id": 11918,
          "important": false,
          "monitor_id": 5,
          "status": 1,
          "msg": "200 - OK",
          "time": "2025-12-31 09:55:54.014",
          "ping": 19,
          "duration": 60,
          "down_count": 0
        },
        {
          "id": 11921,
          "important": false,
          "monitor_id": 5,
          "status": 1,
          "msg": "200 - OK",
          "time": "2025-12-31 09:56:54.036",
          "ping": 26,
          "duration": 60,
          "down_count": 0
        },
        {
          "id": 11924,
          "important": false,
          "monitor_id": 5,
          "status": 1,
          "msg": "200 - OK",
          "time": "2025-12-31 09:57:54.066",
          "ping": 13,
          "duration": 60,
          "down_count": 0
        },
        {
          "id": 11927,
          "important": false,
          "monitor_id": 5,
          "status": 1,
          "msg": "200 - OK",
          "time": "2025-12-31 09:58:54.083",
          "ping": 11,
          "duration": 60,
          "down_count": 0
        },
        {
          "id": 11930,
          "important": false,
          "monitor_id": 5,
          "status": 1,
          "msg": "200 - OK",
          "time": "2025-12-31 09:59:54.098",
          "ping": 12,
          "duration": 60,
          "down_count": 0
        },
        {
          "id": 11933,
          "important": false,
          "monitor_id": 5,
          "status": 1,
          "msg": "200 - OK",
          "time": "2025-12-31 10:00:54.113",
          "ping": 12,
          "duration": 60,
          "down_count": 0
        },
        {
          "id": 11936,
          "important": false,
          "monitor_id": 5,
          "status": 1,
          "msg": "200 - OK",
          "time": "2025-12-31 10:01:54.127",
          "ping": 10,
          "duration": 60,
          "down_count": 0
        },
        {
          "id": 11939,
          "important": false,
          "monitor_id": 5,
          "status": 1,
          "msg": "200 - OK",
          "time": "2025-12-31 10:02:54.141",
          "ping": 10,
          "duration": 60,
          "down_count": 0
        },
        {
          "id": 11942,
          "important": false,
          "monitor_id": 5,
          "status": 1,
          "msg": "200 - OK",
          "time": "2025-12-31 10:03:54.159",
          "ping": 21,
          "duration": 60,
          "down_count": 0
        },
        {
          "id": 11945,
          "important": false,
          "monitor_id": 5,
          "status": 1,
          "msg": "200 - OK",
          "time": "2025-12-31 10:04:54.210",
          "ping": 12,
          "duration": 60,
          "down_count": 0
        },
        {
          "id": 11948,
          "important": false,
          "monitor_id": 5,
          "status": 1,
          "msg": "200 - OK",
          "time": "2025-12-31 10:05:54.224",
          "ping": 13,
          "duration": 60,
          "down_count": 0
        },
        {
          "id": 11951,
          "important": false,
          "monitor_id": 5,
          "status": 1,
          "msg": "200 - OK",
          "time": "2025-12-31 10:06:54.241",
          "ping": 14,
          "duration": 60,
          "down_count": 0
        },
        {
          "id": 11954,
          "important": false,
          "monitor_id": 5,
          "status": 1,
          "msg": "200 - OK",
          "time": "2025-12-31 10:07:54.261",
          "ping": 12,
          "duration": 60,
          "down_count": 0
        },
        {
          "id": 11957,
          "important": false,
          "monitor_id": 5,
          "status": 1,
          "msg": "200 - OK",
          "time": "2025-12-31 10:08:54.276",
          "ping": 15,
          "duration": 60,
          "down_count": 0
        },
        {
          "id": 11960,
          "important": false,
          "monitor_id": 5,
          "status": 1,
          "msg": "200 - OK",
          "time": "2025-12-31 10:09:54.294",
          "ping": 11,
          "duration": 60,
          "down_count": 0
        },
        {
          "id": 11963,
          "important": false,
          "monitor_id": 5,
          "status": 1,
          "msg": "200 - OK",
          "time": "2025-12-31 10:10:54.308",
          "ping": 10,
          "duration": 60,
          "down_count": 0
        },
        {
          "id": 11966,
          "important": false,
          "monitor_id": 5,
          "status": 1,
          "msg": "200 - OK",
          "time": "2025-12-31 10:11:54.323",
          "ping": 10,
          "duration": 60,
          "down_count": 0
        },
        {
          "id": 11969,
          "important": false,
          "monitor_id": 5,
          "status": 1,
          "msg": "200 - OK",
          "time": "2025-12-31 10:12:54.336",
          "ping": 14,
          "duration": 60,
          "down_count": 0
        },
        {
          "id": 11972,
          "important": false,
          "monitor_id": 5,
          "status": 1,
          "msg": "200 - OK",
          "time": "2025-12-31 10:13:54.354",
          "ping": 10,
          "duration": 60,
          "down_count": 0
        },
        {
          "id": 11975,
          "important": false,
          "monitor_id": 5,
          "status": 1,
          "msg": "200 - OK",
          "time": "2025-12-31 10:14:54.366",
          "ping": 10,
          "duration": 60,
          "down_count": 0
        },
        {
          "id": 11978,
          "important": false,
          "monitor_id": 5,
          "status": 1,
          "msg": "200 - OK",
          "time": "2025-12-31 10:15:54.382",
          "ping": 13,
          "duration": 60,
          "down_count": 0
        },
        {
          "id": 11981,
          "important": false,
          "monitor_id": 5,
          "status": 1,
          "msg": "200 - OK",
          "time": "2025-12-31 10:16:54.402",
          "ping": 11,
          "duration": 60,
          "down_count": 0
        },
        {
          "id": 11984,
          "important": false,
          "monitor_id": 5,
          "status": 1,
          "msg": "200 - OK",
          "time": "2025-12-31 10:17:54.417",
          "ping": 14,
          "duration": 60,
          "down_count": 0
        },
        {
          "id": 11987,
          "important": false,
          "monitor_id": 5,
          "status": 1,
          "msg": "200 - OK",
          "time": "2025-12-31 10:18:54.434",
          "ping": 24,
          "duration": 60,
          "down_count": 0
        },
        {
          "id": 11990,
          "important": false,
          "monitor_id": 5,
          "status": 1,
          "msg": "200 - OK",
          "time": "2025-12-31 10:19:54.472",
          "ping": 19,
          "duration": 60,
          "down_count": 0
        },
        {
          "id": 11993,
          "important": false,
          "monitor_id": 5,
          "status": 1,
          "msg": "200 - OK",
          "time": "2025-12-31 10:20:54.495",
          "ping": 27,
          "duration": 60,
          "down_count": 0
        },
        {
          "id": 11996,
          "important": false,
          "monitor_id": 5,
          "status": 1,
          "msg": "200 - OK",
          "time": "2025-12-31 10:21:54.529",
          "ping": 11,
          "duration": 60,
          "down_count": 0
        },
        {
          "id": 11999,
          "important": false,
          "monitor_id": 5,
          "status": 1,
          "msg": "200 - OK",
          "time": "2025-12-31 10:22:54.549",
          "ping": 9,
          "duration": 60,
          "down_count": 0
        },
        {
          "id": 12002,
          "important": false,
          "monitor_id": 5,
          "status": 1,
          "msg": "200 - OK",
          "time": "2025-12-31 10:23:54.566",
          "ping": 14,
          "duration": 60,
          "down_count": 0
        },
        {
          "id": 12005,
          "important": false,
          "monitor_id": 5,
          "status": 1,
          "msg": "200 - OK",
          "time": "2025-12-31 10:24:54.599",
          "ping": 25,
          "duration": 60,
          "down_count": 0
        },
        {
          "id": 12008,
          "important": false,
          "monitor_id": 5,
          "status": 1,
          "msg": "200 - OK",
          "time": "2025-12-31 10:25:54.662",
          "ping": 18,
          "duration": 60,
          "down_count": 0
        },
        {
          "id": 12011,
          "important": false,
          "monitor_id": 5,
          "status": 1,
          "msg": "200 - OK",
          "time": "2025-12-31 10:26:54.682",
          "ping": 12,
          "duration": 60,
          "down_count": 0
        },
        {
          "id": 12014,
          "important": false,
          "monitor_id": 5,
          "status": 1,
          "msg": "200 - OK",
          "time": "2025-12-31 10:27:54.697",
          "ping": 11,
          "duration": 60,
          "down_count": 0
        },
        {
          "id": 12017,
          "important": false,
          "monitor_id": 5,
          "status": 1,
          "msg": "200 - OK",
          "time": "2025-12-31 10:28:54.712",
          "ping": 13,
          "duration": 60,
          "down_count": 0
        },
        {
          "id": 12020,
          "important": false,
          "monitor_id": 5,
          "status": 1,
          "msg": "200 - OK",
          "time": "2025-12-31 10:29:54.727",
          "ping": 14,
          "duration": 60,
          "down_count": 0
        },
        {
          "id": 12023,
          "important": false,
          "monitor_id": 5,
          "status": 1,
          "msg": "200 - OK",
          "time": "2025-12-31 10:30:54.744",
          "ping": 12,
          "duration": 60,
          "down_count": 0
        },
        {
          "id": 12026,
          "important": false,
          "monitor_id": 5,
          "status": 1,
          "msg": "200 - OK",
          "time": "2025-12-31 10:31:54.759",
          "ping": 15,
          "duration": 60,
          "down_count": 0
        },
        {
          "id": 12029,
          "important": false,
          "monitor_id": 5,
          "status": 1,
          "msg": "200 - OK",
          "time": "2025-12-31 10:32:54.777",
          "ping": 11,
          "duration": 60,
          "down_count": 0
        },
        {
          "id": 12032,
          "important": false,
          "monitor_id": 5,
          "status": 1,
          "msg": "200 - OK",
          "time": "2025-12-31 10:33:54.793",
          "ping": 14,
          "duration": 60,
          "down_count": 0
        },
        {
          "id": 12035,
          "important": false,
          "monitor_id": 5,
          "status": 1,
          "msg": "200 - OK",
          "time": "2025-12-31 10:34:54.810",
          "ping": 12,
          "duration": 60,
          "down_count": 0
        },
        {
          "id": 12038,
          "important": false,
          "monitor_id": 5,
          "status": 1,
          "msg": "200 - OK",
          "time": "2025-12-31 10:35:54.827",
          "ping": 14,
          "duration": 60,
          "down_count": 0
        },
        {
          "id": 12041,
          "important": false,
          "monitor_id": 5,
          "status": 1,
          "msg": "200 - OK",
          "time": "2025-12-31 10:36:54.846",
          "ping": 13,
          "duration": 60,
          "down_count": 0
        },
        {
          "id": 12044,
          "important": false,
          "monitor_id": 5,
          "status": 1,
          "msg": "200 - OK",
          "time": "2025-12-31 10:37:54.863",
          "ping": 13,
          "duration": 60,
          "down_count": 0
        },
        {
          "id": 12047,
          "important": false,
          "monitor_id": 5,
          "status": 1,
          "msg": "200 - OK",
          "time": "2025-12-31 10:38:54.880",
          "ping": 12,
          "duration": 60,
          "down_count": 0
        },
        {
          "id": 12050,
          "important": false,
          "monitor_id": 5,
          "status": 1,
          "msg": "200 - OK",
          "time": "2025-12-31 10:39:54.895",
          "ping": 10,
          "duration": 60,
          "down_count": 0
        },
        {
          "id": 12053,
          "important": false,
          "monitor_id": 5,
          "status": 1,
          "msg": "200 - OK",
          "time": "2025-12-31 10:40:54.909",
          "ping": 12,
          "duration": 60,
          "down_count": 0
        },
        {
          "id": 12056,
          "important": false,
          "monitor_id": 5,
          "status": 1,
          "msg": "200 - OK",
          "time": "2025-12-31 10:41:54.924",
          "ping": 9,
          "duration": 60,
          "down_count": 0
        },
        {
          "id": 12059,
          "important": false,
          "monitor_id": 5,
          "status": 1,
          "msg": "200 - OK",
          "time": "2025-12-31 10:42:54.937",
          "ping": 13,
          "duration": 60,
          "down_count": 0
        },
        {
          "id": 12062,
          "important": false,
          "monitor_id": 5,
          "status": 1,
          "msg": "200 - OK",
          "time": "2025-12-31 10:43:54.952",
          "ping": 13,
          "duration": 60,
          "down_count": 0
        },
        {
          "id": 12065,
          "important": false,
          "monitor_id": 5,
          "status": 1,
          "msg": "200 - OK",
          "time": "2025-12-31 10:44:54.969",
          "ping": 11,
          "duration": 60,
          "down_count": 0
        },
        {
          "id": 12068,
          "important": false,
          "monitor_id": 5,
          "status": 1,
          "msg": "200 - OK",
          "time": "2025-12-31 10:45:54.983",
          "ping": 11,
          "duration": 60,
          "down_count": 0
        },
        {
          "id": 12071,
          "important": false,
          "monitor_id": 5,
          "status": 1,
          "msg": "200 - OK",
          "time": "2025-12-31 10:46:55.002",
          "ping": 39,
          "duration": 60,
          "down_count": 0
        },
        {
          "id": 12074,
          "important": false,
          "monitor_id": 5,
          "status": 1,
          "msg": "200 - OK",
          "time": "2025-12-31 10:47:55.056",
          "ping": 13,
          "duration": 60,
          "down_count": 0
        },
        {
          "id": 12077,
          "important": false,
          "monitor_id": 5,
          "status": 1,
          "msg": "200 - OK",
          "time": "2025-12-31 10:48:55.072",
          "ping": 10,
          "duration": 60,
          "down_count": 0
        },
        {
          "id": 12080,
          "important": false,
          "monitor_id": 5,
          "status": 1,
          "msg": "200 - OK",
          "time": "2025-12-31 10:49:55.086",
          "ping": 11,
          "duration": 60,
          "down_count": 0
        },
        {
          "id": 12083,
          "important": false,
          "monitor_id": 5,
          "status": 1,
          "msg": "200 - OK",
          "time": "2025-12-31 10:50:55.101",
          "ping": 10,
          "duration": 60,
          "down_count": 0
        },
        {
          "id": 12086,
          "important": false,
          "monitor_id": 5,
          "status": 1,
          "msg": "200 - OK",
          "time": "2025-12-31 10:51:55.115",
          "ping": 14,
          "duration": 60,
          "down_count": 0
        },
        {
          "id": 12089,
          "important": false,
          "monitor_id": 5,
          "status": 1,
          "msg": "200 - OK",
          "time": "2025-12-31 10:52:55.132",
          "ping": 13,
          "duration": 60,
          "down_count": 0
        },
        {
          "id": 12092,
          "important": false,
          "monitor_id": 5,
          "status": 1,
          "msg": "200 - OK",
          "time": "2025-12-31 10:53:55.150",
          "ping": 11,
          "duration": 60,
          "down_count": 0
        },
        {
          "id": 12095,
          "important": false,
          "monitor_id": 5,
          "status": 1,
          "msg": "200 - OK",
          "time": "2025-12-31 10:54:55.165",
          "ping": 12,
          "duration": 60,
          "down_count": 0
        },
        {
          "id": 12098,
          "important": false,
          "monitor_id": 5,
          "status": 1,
          "msg": "200 - OK",
          "time": "2025-12-31 10:55:55.179",
          "ping": 13,
          "duration": 60,
          "down_count": 0
        },
        {
          "id": 12101,
          "important": false,
          "monitor_id": 5,
          "status": 1,
          "msg": "200 - OK",
          "time": "2025-12-31 10:56:55.196",
          "ping": 14,
          "duration": 60,
          "down_count": 0
        },
        {
          "id": 12104,
          "important": false,
          "monitor_id": 5,
          "status": 1,
          "msg": "200 - OK",
          "time": "2025-12-31 10:57:55.214",
          "ping": 11,
          "duration": 60,
          "down_count": 0
        },
        {
          "id": 12107,
          "important": false,
          "monitor_id": 5,
          "status": 1,
          "msg": "200 - OK",
          "time": "2025-12-31 10:58:55.229",
          "ping": 11,
          "duration": 60,
          "down_count": 0
        },
        {
          "id": 12110,
          "important": false,
          "monitor_id": 5,
          "status": 1,
          "msg": "200 - OK",
          "time": "2025-12-31 10:59:55.243",
          "ping": 11,
          "duration": 60,
          "down_count": 0
        },
        {
          "id": 12113,
          "important": false,
          "monitor_id": 5,
          "status": 1,
          "msg": "200 - OK",
          "time": "2025-12-31 11:00:55.257",
          "ping": 12,
          "duration": 60,
          "down_count": 0
        },
        {
          "id": 12116,
          "important": false,
          "monitor_id": 5,
          "status": 1,
          "msg": "200 - OK",
          "time": "2025-12-31 11:01:55.273",
          "ping": 13,
          "duration": 60,
          "down_count": 0
        },
        {
          "id": 12119,
          "important": false,
          "monitor_id": 5,
          "status": 1,
          "msg": "200 - OK",
          "time": "2025-12-31 11:02:55.290",
          "ping": 12,
          "duration": 60,
          "down_count": 0
        },
        {
          "id": 12122,
          "important": false,
          "monitor_id": 5,
          "status": 1,
          "msg": "200 - OK",
          "time": "2025-12-31 11:03:55.307",
          "ping": 16,
          "duration": 60,
          "down_count": 0
        },
        {
          "id": 12125,
          "important": false,
          "monitor_id": 5,
          "status": 1,
          "msg": "200 - OK",
          "time": "2025-12-31 11:04:55.329",
          "ping": 13,
          "duration": 60,
          "down_count": 0
        },
        {
          "id": 12128,
          "important": false,
          "monitor_id": 5,
          "status": 1,
          "msg": "200 - OK",
          "time": "2025-12-31 11:05:55.344",
          "ping": 12,
          "duration": 60,
          "down_count": 0
        },
        {
          "id": 12131,
          "important": false,
          "monitor_id": 5,
          "status": 1,
          "msg": "200 - OK",
          "time": "2025-12-31 11:06:55.362",
          "ping": 12,
          "duration": 60,
          "down_count": 0
        },
        {
          "id": 12134,
          "important": false,
          "monitor_id": 5,
          "status": 1,
          "msg": "200 - OK",
          "time": "2025-12-31 11:07:55.377",
          "ping": 13,
          "duration": 60,
          "down_count": 0
        },
        {
          "id": 12137,
          "important": false,
          "monitor_id": 5,
          "status": 1,
          "msg": "200 - OK",
          "time": "2025-12-31 11:08:55.393",
          "ping": 17,
          "duration": 60,
          "down_count": 0
        },
        {
          "id": 12140,
          "important": false,
          "monitor_id": 5,
          "status": 1,
          "msg": "200 - OK",
          "time": "2025-12-31 11:09:55.413",
          "ping": 16,
          "duration": 60,
          "down_count": 0
        },
        {
          "id": 12143,
          "important": false,
          "monitor_id": 5,
          "status": 1,
          "msg": "200 - OK",
          "time": "2025-12-31 11:10:55.432",
          "ping": 13,
          "duration": 60,
          "down_count": 0
        },
        {
          "id": 12146,
          "important": false,
          "monitor_id": 5,
          "status": 1,
          "msg": "200 - OK",
          "time": "2025-12-31 11:11:55.448",
          "ping": 11,
          "duration": 60,
          "down_count": 0
        },
        {
          "id": 12149,
          "important": false,
          "monitor_id": 5,
          "status": 1,
          "msg": "200 - OK",
          "time": "2025-12-31 11:12:55.462",
          "ping": 13,
          "duration": 60,
          "down_count": 0
        },
        {
          "id": 12152,
          "important": false,
          "monitor_id": 5,
          "status": 1,
          "msg": "200 - OK",
          "time": "2025-12-31 11:13:55.479",
          "ping": 14,
          "duration": 60,
          "down_count": 0
        },
        {
          "id": 12155,
          "important": false,
          "monitor_id": 5,
          "status": 1,
          "msg": "200 - OK",
          "time": "2025-12-31 11:14:55.495",
          "ping": 12,
          "duration": 60,
          "down_count": 0
        },
        {
          "id": 12158,
          "important": false,
          "monitor_id": 5,
          "status": 1,
          "msg": "200 - OK",
          "time": "2025-12-31 11:15:55.511",
          "ping": 13,
          "duration": 60,
          "down_count": 0
        },
        {
          "id": 12161,
          "important": false,
          "monitor_id": 5,
          "status": 1,
          "msg": "200 - OK",
          "time": "2025-12-31 11:16:55.527",
          "ping": 13,
          "duration": 60,
          "down_count": 0
        },
        {
          "id": 12164,
          "important": false,
          "monitor_id": 5,
          "status": 1,
          "msg": "200 - OK",
          "time": "2025-12-31 11:17:55.544",
          "ping": 12,
          "duration": 60,
          "down_count": 0
        },
        {
          "id": 12167,
          "important": false,
          "monitor_id": 5,
          "status": 1,
          "msg": "200 - OK",
          "time": "2025-12-31 11:18:55.560",
          "ping": 12,
          "duration": 60,
          "down_count": 0
        },
        {
          "id": 12170,
          "important": false,
          "monitor_id": 5,
          "status": 1,
          "msg": "200 - OK",
          "time": "2025-12-31 11:19:55.575",
          "ping": 13,
          "duration": 60,
          "down_count": 0
        },
        {
          "id": 12173,
          "important": false,
          "monitor_id": 5,
          "status": 1,
          "msg": "200 - OK",
          "time": "2025-12-31 11:20:55.593",
          "ping": 14,
          "duration": 60,
          "down_count": 0
        },
        {
          "id": 12176,
          "important": false,
          "monitor_id": 5,
          "status": 1,
          "msg": "200 - OK",
          "time": "2025-12-31 11:21:55.610",
          "ping": 11,
          "duration": 60,
          "down_count": 0
        },
        {
          "id": 12179,
          "important": false,
          "monitor_id": 5,
          "status": 1,
          "msg": "200 - OK",
          "time": "2025-12-31 11:22:55.626",
          "ping": 13,
          "duration": 60,
          "down_count": 0
        },
        {
          "id": 12182,
          "important": false,
          "monitor_id": 5,
          "status": 1,
          "msg": "200 - OK",
          "time": "2025-12-31 11:23:55.643",
          "ping": 13,
          "duration": 60,
          "down_count": 0
        }
      ]
    },
    "6": {
      "monitor": {
        "id": 6,
        "name": "Verify Truth",
        "type": "MonitorType.HTTP",
        "active": true
      },
      "count": 100,
      "beats": [
        {
          "id": 11886,
          "important": false,
          "monitor_id": 6,
          "status": 1,
          "msg": "200 - OK",
          "time": "2025-12-31 09:45:33.520",
          "ping": 122,
          "duration": 60,
          "down_count": 0
        },
        {
          "id": 11889,
          "important": false,
          "monitor_id": 6,
          "status": 1,
          "msg": "200 - OK",
          "time": "2025-12-31 09:46:33.648",
          "ping": 111,
          "duration": 60,
          "down_count": 0
        },
        {
          "id": 11892,
          "important": false,
          "monitor_id": 6,
          "status": 1,
          "msg": "200 - OK",
          "time": "2025-12-31 09:47:33.763",
          "ping": 121,
          "duration": 60,
          "down_count": 0
        },
        {
          "id": 11895,
          "important": false,
          "monitor_id": 6,
          "status": 1,
          "msg": "200 - OK",
          "time": "2025-12-31 09:48:33.886",
          "ping": 120,
          "duration": 60,
          "down_count": 0
        },
        {
          "id": 11898,
          "important": false,
          "monitor_id": 6,
          "status": 1,
          "msg": "200 - OK",
          "time": "2025-12-31 09:49:34.010",
          "ping": 125,
          "duration": 60,
          "down_count": 0
        },
        {
          "id": 11901,
          "important": false,
          "monitor_id": 6,
          "status": 1,
          "msg": "200 - OK",
          "time": "2025-12-31 09:50:34.141",
          "ping": 119,
          "duration": 60,
          "down_count": 0
        },
        {
          "id": 11904,
          "important": false,
          "monitor_id": 6,
          "status": 1,
          "msg": "200 - OK",
          "time": "2025-12-31 09:51:34.265",
          "ping": 125,
          "duration": 60,
          "down_count": 0
        },
        {
          "id": 11907,
          "important": false,
          "monitor_id": 6,
          "status": 1,
          "msg": "200 - OK",
          "time": "2025-12-31 09:52:34.395",
          "ping": 136,
          "duration": 60,
          "down_count": 0
        },
        {
          "id": 11910,
          "important": false,
          "monitor_id": 6,
          "status": 1,
          "msg": "200 - OK",
          "time": "2025-12-31 09:53:34.538",
          "ping": 130,
          "duration": 60,
          "down_count": 0
        },
        {
          "id": 11913,
          "important": false,
          "monitor_id": 6,
          "status": 1,
          "msg": "200 - OK",
          "time": "2025-12-31 09:54:34.672",
          "ping": 165,
          "duration": 60,
          "down_count": 0
        },
        {
          "id": 11916,
          "important": true,
          "monitor_id": 6,
          "status": 0,
          "msg": "Request failed with status code 503",
          "time": "2025-12-31 09:55:34.841",
          "ping": null,
          "duration": 60,
          "down_count": 0
        },
        {
          "id": 11919,
          "important": true,
          "monitor_id": 6,
          "status": 1,
          "msg": "200 - OK",
          "time": "2025-12-31 09:56:35.068",
          "ping": 119,
          "duration": 60,
          "down_count": 0
        },
        {
          "id": 11922,
          "important": false,
          "monitor_id": 6,
          "status": 1,
          "msg": "200 - OK",
          "time": "2025-12-31 09:57:35.282",
          "ping": 139,
          "duration": 60,
          "down_count": 0
        },
        {
          "id": 11925,
          "important": false,
          "monitor_id": 6,
          "status": 1,
          "msg": "200 - OK",
          "time": "2025-12-31 09:58:35.427",
          "ping": 127,
          "duration": 60,
          "down_count": 0
        },
        {
          "id": 11928,
          "important": false,
          "monitor_id": 6,
          "status": 1,
          "msg": "200 - OK",
          "time": "2025-12-31 09:59:35.559",
          "ping": 118,
          "duration": 60,
          "down_count": 0
        },
        {
          "id": 11931,
          "important": false,
          "monitor_id": 6,
          "status": 1,
          "msg": "200 - OK",
          "time": "2025-12-31 10:00:35.684",
          "ping": 124,
          "duration": 60,
          "down_count": 0
        },
        {
          "id": 11934,
          "important": false,
          "monitor_id": 6,
          "status": 1,
          "msg": "200 - OK",
          "time": "2025-12-31 10:01:35.815",
          "ping": 141,
          "duration": 60,
          "down_count": 0
        },
        {
          "id": 11937,
          "important": false,
          "monitor_id": 6,
          "status": 1,
          "msg": "200 - OK",
          "time": "2025-12-31 10:02:35.960",
          "ping": 106,
          "duration": 60,
          "down_count": 0
        },
        {
          "id": 11940,
          "important": false,
          "monitor_id": 6,
          "status": 1,
          "msg": "200 - OK",
          "time": "2025-12-31 10:03:36.071",
          "ping": 101,
          "duration": 60,
          "down_count": 0
        },
        {
          "id": 11943,
          "important": false,
          "monitor_id": 6,
          "status": 1,
          "msg": "200 - OK",
          "time": "2025-12-31 10:04:36.175",
          "ping": 103,
          "duration": 60,
          "down_count": 0
        },
        {
          "id": 11946,
          "important": true,
          "monitor_id": 6,
          "status": 0,
          "msg": "Request failed with status code 503",
          "time": "2025-12-31 10:05:36.283",
          "ping": null,
          "duration": 60,
          "down_count": 0
        },
        {
          "id": 11949,
          "important": true,
          "monitor_id": 6,
          "status": 1,
          "msg": "200 - OK",
          "time": "2025-12-31 10:06:36.504",
          "ping": 137,
          "duration": 60,
          "down_count": 0
        },
        {
          "id": 11952,
          "important": false,
          "monitor_id": 6,
          "status": 1,
          "msg": "200 - OK",
          "time": "2025-12-31 10:07:36.722",
          "ping": 106,
          "duration": 60,
          "down_count": 0
        },
        {
          "id": 11955,
          "important": false,
          "monitor_id": 6,
          "status": 1,
          "msg": "200 - OK",
          "time": "2025-12-31 10:08:36.833",
          "ping": 143,
          "duration": 60,
          "down_count": 0
        },
        {
          "id": 11958,
          "important": false,
          "monitor_id": 6,
          "status": 1,
          "msg": "200 - OK",
          "time": "2025-12-31 10:09:36.982",
          "ping": 120,
          "duration": 60,
          "down_count": 0
        },
        {
          "id": 11961,
          "important": false,
          "monitor_id": 6,
          "status": 1,
          "msg": "200 - OK",
          "time": "2025-12-31 10:10:37.106",
          "ping": 109,
          "duration": 60,
          "down_count": 0
        },
        {
          "id": 11964,
          "important": false,
          "monitor_id": 6,
          "status": 1,
          "msg": "200 - OK",
          "time": "2025-12-31 10:11:37.219",
          "ping": 111,
          "duration": 60,
          "down_count": 0
        },
        {
          "id": 11967,
          "important": false,
          "monitor_id": 6,
          "status": 1,
          "msg": "200 - OK",
          "time": "2025-12-31 10:12:37.335",
          "ping": 107,
          "duration": 60,
          "down_count": 0
        },
        {
          "id": 11970,
          "important": false,
          "monitor_id": 6,
          "status": 1,
          "msg": "200 - OK",
          "time": "2025-12-31 10:13:37.447",
          "ping": 134,
          "duration": 60,
          "down_count": 0
        },
        {
          "id": 11973,
          "important": false,
          "monitor_id": 6,
          "status": 1,
          "msg": "200 - OK",
          "time": "2025-12-31 10:14:37.610",
          "ping": 122,
          "duration": 60,
          "down_count": 0
        },
        {
          "id": 11976,
          "important": false,
          "monitor_id": 6,
          "status": 1,
          "msg": "200 - OK",
          "time": "2025-12-31 10:15:37.737",
          "ping": 120,
          "duration": 60,
          "down_count": 0
        },
        {
          "id": 11979,
          "important": true,
          "monitor_id": 6,
          "status": 0,
          "msg": "Request failed with status code 503",
          "time": "2025-12-31 10:16:37.862",
          "ping": null,
          "duration": 60,
          "down_count": 0
        },
        {
          "id": 11982,
          "important": true,
          "monitor_id": 6,
          "status": 1,
          "msg": "200 - OK",
          "time": "2025-12-31 10:17:38.152",
          "ping": 109,
          "duration": 60,
          "down_count": 0
        },
        {
          "id": 11985,
          "important": false,
          "monitor_id": 6,
          "status": 1,
          "msg": "200 - OK",
          "time": "2025-12-31 10:18:38.557",
          "ping": 122,
          "duration": 60,
          "down_count": 0
        },
        {
          "id": 11988,
          "important": false,
          "monitor_id": 6,
          "status": 1,
          "msg": "200 - OK",
          "time": "2025-12-31 10:19:38.683",
          "ping": 118,
          "duration": 60,
          "down_count": 0
        },
        {
          "id": 11991,
          "important": false,
          "monitor_id": 6,
          "status": 1,
          "msg": "200 - OK",
          "time": "2025-12-31 10:20:38.807",
          "ping": 141,
          "duration": 60,
          "down_count": 0
        },
        {
          "id": 11994,
          "important": false,
          "monitor_id": 6,
          "status": 1,
          "msg": "200 - OK",
          "time": "2025-12-31 10:21:38.953",
          "ping": 130,
          "duration": 60,
          "down_count": 0
        },
        {
          "id": 11997,
          "important": false,
          "monitor_id": 6,
          "status": 1,
          "msg": "200 - OK",
          "time": "2025-12-31 10:22:39.089",
          "ping": 105,
          "duration": 60,
          "down_count": 0
        },
        {
          "id": 12000,
          "important": false,
          "monitor_id": 6,
          "status": 1,
          "msg": "200 - OK",
          "time": "2025-12-31 10:23:39.200",
          "ping": 105,
          "duration": 60,
          "down_count": 0
        },
        {
          "id": 12003,
          "important": false,
          "monitor_id": 6,
          "status": 1,
          "msg": "200 - OK",
          "time": "2025-12-31 10:24:39.308",
          "ping": 146,
          "duration": 60,
          "down_count": 0
        },
        {
          "id": 12006,
          "important": false,
          "monitor_id": 6,
          "status": 1,
          "msg": "200 - OK",
          "time": "2025-12-31 10:25:39.460",
          "ping": 105,
          "duration": 60,
          "down_count": 0
        },
        {
          "id": 12009,
          "important": false,
          "monitor_id": 6,
          "status": 1,
          "msg": "200 - OK",
          "time": "2025-12-31 10:26:39.570",
          "ping": 116,
          "duration": 60,
          "down_count": 0
        },
        {
          "id": 12012,
          "important": false,
          "monitor_id": 6,
          "status": 1,
          "msg": "200 - OK",
          "time": "2025-12-31 10:27:39.691",
          "ping": 140,
          "duration": 60,
          "down_count": 0
        },
        {
          "id": 12015,
          "important": false,
          "monitor_id": 6,
          "status": 1,
          "msg": "200 - OK",
          "time": "2025-12-31 10:28:39.835",
          "ping": 116,
          "duration": 60,
          "down_count": 0
        },
        {
          "id": 12018,
          "important": false,
          "monitor_id": 6,
          "status": 1,
          "msg": "200 - OK",
          "time": "2025-12-31 10:29:39.995",
          "ping": 116,
          "duration": 60,
          "down_count": 0
        },
        {
          "id": 12021,
          "important": false,
          "monitor_id": 6,
          "status": 1,
          "msg": "200 - OK",
          "time": "2025-12-31 10:30:40.118",
          "ping": 107,
          "duration": 60,
          "down_count": 0
        },
        {
          "id": 12024,
          "important": false,
          "monitor_id": 6,
          "status": 1,
          "msg": "200 - OK",
          "time": "2025-12-31 10:31:40.229",
          "ping": 109,
          "duration": 60,
          "down_count": 0
        },
        {
          "id": 12027,
          "important": false,
          "monitor_id": 6,
          "status": 1,
          "msg": "200 - OK",
          "time": "2025-12-31 10:32:40.342",
          "ping": 237,
          "duration": 60,
          "down_count": 0
        },
        {
          "id": 12030,
          "important": false,
          "monitor_id": 6,
          "status": 1,
          "msg": "200 - OK",
          "time": "2025-12-31 10:33:40.583",
          "ping": 106,
          "duration": 60,
          "down_count": 0
        },
        {
          "id": 12033,
          "important": false,
          "monitor_id": 6,
          "status": 1,
          "msg": "200 - OK",
          "time": "2025-12-31 10:34:40.705",
          "ping": 102,
          "duration": 60,
          "down_count": 0
        },
        {
          "id": 12036,
          "important": false,
          "monitor_id": 6,
          "status": 1,
          "msg": "200 - OK",
          "time": "2025-12-31 10:35:40.812",
          "ping": 112,
          "duration": 60,
          "down_count": 0
        },
        {
          "id": 12039,
          "important": false,
          "monitor_id": 6,
          "status": 1,
          "msg": "200 - OK",
          "time": "2025-12-31 10:36:40.929",
          "ping": 104,
          "duration": 60,
          "down_count": 0
        },
        {
          "id": 12042,
          "important": true,
          "monitor_id": 6,
          "status": 0,
          "msg": "Request failed with status code 503",
          "time": "2025-12-31 10:37:41.036",
          "ping": null,
          "duration": 60,
          "down_count": 0
        },
        {
          "id": 12045,
          "important": true,
          "monitor_id": 6,
          "status": 1,
          "msg": "200 - OK",
          "time": "2025-12-31 10:38:41.271",
          "ping": 129,
          "duration": 60,
          "down_count": 0
        },
        {
          "id": 12048,
          "important": false,
          "monitor_id": 6,
          "status": 1,
          "msg": "200 - OK",
          "time": "2025-12-31 10:39:41.473",
          "ping": 106,
          "duration": 60,
          "down_count": 0
        },
        {
          "id": 12051,
          "important": false,
          "monitor_id": 6,
          "status": 1,
          "msg": "200 - OK",
          "time": "2025-12-31 10:40:41.586",
          "ping": 106,
          "duration": 60,
          "down_count": 0
        },
        {
          "id": 12054,
          "important": false,
          "monitor_id": 6,
          "status": 1,
          "msg": "200 - OK",
          "time": "2025-12-31 10:41:41.695",
          "ping": 107,
          "duration": 60,
          "down_count": 0
        },
        {
          "id": 12057,
          "important": false,
          "monitor_id": 6,
          "status": 1,
          "msg": "200 - OK",
          "time": "2025-12-31 10:42:41.805",
          "ping": 105,
          "duration": 60,
          "down_count": 0
        },
        {
          "id": 12060,
          "important": false,
          "monitor_id": 6,
          "status": 1,
          "msg": "200 - OK",
          "time": "2025-12-31 10:43:41.913",
          "ping": 132,
          "duration": 60,
          "down_count": 0
        },
        {
          "id": 12063,
          "important": false,
          "monitor_id": 6,
          "status": 1,
          "msg": "200 - OK",
          "time": "2025-12-31 10:44:42.107",
          "ping": 134,
          "duration": 60,
          "down_count": 0
        },
        {
          "id": 12066,
          "important": false,
          "monitor_id": 6,
          "status": 1,
          "msg": "200 - OK",
          "time": "2025-12-31 10:45:42.247",
          "ping": 445,
          "duration": 60,
          "down_count": 0
        },
        {
          "id": 12069,
          "important": true,
          "monitor_id": 6,
          "status": 0,
          "msg": "Request failed with status code 503",
          "time": "2025-12-31 10:46:42.697",
          "ping": null,
          "duration": 60,
          "down_count": 0
        },
        {
          "id": 12072,
          "important": true,
          "monitor_id": 6,
          "status": 1,
          "msg": "200 - OK",
          "time": "2025-12-31 10:47:42.889",
          "ping": 102,
          "duration": 60,
          "down_count": 0
        },
        {
          "id": 12075,
          "important": false,
          "monitor_id": 6,
          "status": 1,
          "msg": "200 - OK",
          "time": "2025-12-31 10:48:43.110",
          "ping": 108,
          "duration": 60,
          "down_count": 0
        },
        {
          "id": 12078,
          "important": false,
          "monitor_id": 6,
          "status": 1,
          "msg": "200 - OK",
          "time": "2025-12-31 10:49:43.223",
          "ping": 98,
          "duration": 60,
          "down_count": 0
        },
        {
          "id": 12081,
          "important": false,
          "monitor_id": 6,
          "status": 1,
          "msg": "200 - OK",
          "time": "2025-12-31 10:50:43.325",
          "ping": 110,
          "duration": 60,
          "down_count": 0
        },
        {
          "id": 12084,
          "important": false,
          "monitor_id": 6,
          "status": 1,
          "msg": "200 - OK",
          "time": "2025-12-31 10:51:43.440",
          "ping": 115,
          "duration": 60,
          "down_count": 0
        },
        {
          "id": 12087,
          "important": false,
          "monitor_id": 6,
          "status": 1,
          "msg": "200 - OK",
          "time": "2025-12-31 10:52:43.559",
          "ping": 109,
          "duration": 60,
          "down_count": 0
        },
        {
          "id": 12090,
          "important": false,
          "monitor_id": 6,
          "status": 1,
          "msg": "200 - OK",
          "time": "2025-12-31 10:53:43.672",
          "ping": 98,
          "duration": 60,
          "down_count": 0
        },
        {
          "id": 12093,
          "important": false,
          "monitor_id": 6,
          "status": 1,
          "msg": "200 - OK",
          "time": "2025-12-31 10:54:43.804",
          "ping": 108,
          "duration": 60,
          "down_count": 0
        },
        {
          "id": 12096,
          "important": true,
          "monitor_id": 6,
          "status": 0,
          "msg": "Request failed with status code 503",
          "time": "2025-12-31 10:55:43.918",
          "ping": null,
          "duration": 60,
          "down_count": 0
        },
        {
          "id": 12099,
          "important": true,
          "monitor_id": 6,
          "status": 1,
          "msg": "200 - OK",
          "time": "2025-12-31 10:56:44.110",
          "ping": 112,
          "duration": 60,
          "down_count": 0
        },
        {
          "id": 12102,
          "important": false,
          "monitor_id": 6,
          "status": 1,
          "msg": "200 - OK",
          "time": "2025-12-31 10:57:44.296",
          "ping": 122,
          "duration": 60,
          "down_count": 0
        },
        {
          "id": 12105,
          "important": false,
          "monitor_id": 6,
          "status": 1,
          "msg": "200 - OK",
          "time": "2025-12-31 10:58:44.421",
          "ping": 106,
          "duration": 60,
          "down_count": 0
        },
        {
          "id": 12108,
          "important": false,
          "monitor_id": 6,
          "status": 1,
          "msg": "200 - OK",
          "time": "2025-12-31 10:59:44.532",
          "ping": 102,
          "duration": 60,
          "down_count": 0
        },
        {
          "id": 12111,
          "important": false,
          "monitor_id": 6,
          "status": 1,
          "msg": "200 - OK",
          "time": "2025-12-31 11:00:44.641",
          "ping": 106,
          "duration": 60,
          "down_count": 0
        },
        {
          "id": 12114,
          "important": false,
          "monitor_id": 6,
          "status": 1,
          "msg": "200 - OK",
          "time": "2025-12-31 11:01:44.752",
          "ping": 120,
          "duration": 60,
          "down_count": 0
        },
        {
          "id": 12117,
          "important": false,
          "monitor_id": 6,
          "status": 1,
          "msg": "200 - OK",
          "time": "2025-12-31 11:02:44.875",
          "ping": 133,
          "duration": 60,
          "down_count": 0
        },
        {
          "id": 12120,
          "important": false,
          "monitor_id": 6,
          "status": 1,
          "msg": "200 - OK",
          "time": "2025-12-31 11:03:45.014",
          "ping": 134,
          "duration": 60,
          "down_count": 0
        },
        {
          "id": 12123,
          "important": false,
          "monitor_id": 6,
          "status": 1,
          "msg": "200 - OK",
          "time": "2025-12-31 11:04:45.153",
          "ping": 123,
          "duration": 60,
          "down_count": 0
        },
        {
          "id": 12126,
          "important": true,
          "monitor_id": 6,
          "status": 0,
          "msg": "Request failed with status code 503",
          "time": "2025-12-31 11:05:45.283",
          "ping": null,
          "duration": 60,
          "down_count": 0
        },
        {
          "id": 12129,
          "important": true,
          "monitor_id": 6,
          "status": 1,
          "msg": "200 - OK",
          "time": "2025-12-31 11:06:45.474",
          "ping": 115,
          "duration": 60,
          "down_count": 0
        },
        {
          "id": 12132,
          "important": false,
          "monitor_id": 6,
          "status": 1,
          "msg": "200 - OK",
          "time": "2025-12-31 11:07:45.665",
          "ping": 120,
          "duration": 60,
          "down_count": 0
        },
        {
          "id": 12135,
          "important": false,
          "monitor_id": 6,
          "status": 1,
          "msg": "200 - OK",
          "time": "2025-12-31 11:08:45.790",
          "ping": 149,
          "duration": 60,
          "down_count": 0
        },
        {
          "id": 12138,
          "important": false,
          "monitor_id": 6,
          "status": 1,
          "msg": "200 - OK",
          "time": "2025-12-31 11:09:45.960",
          "ping": 143,
          "duration": 60,
          "down_count": 0
        },
        {
          "id": 12141,
          "important": false,
          "monitor_id": 6,
          "status": 1,
          "msg": "200 - OK",
          "time": "2025-12-31 11:10:46.109",
          "ping": 116,
          "duration": 60,
          "down_count": 0
        },
        {
          "id": 12144,
          "important": false,
          "monitor_id": 6,
          "status": 1,
          "msg": "200 - OK",
          "time": "2025-12-31 11:11:46.229",
          "ping": 107,
          "duration": 60,
          "down_count": 0
        },
        {
          "id": 12147,
          "important": false,
          "monitor_id": 6,
          "status": 1,
          "msg": "200 - OK",
          "time": "2025-12-31 11:12:46.339",
          "ping": 98,
          "duration": 60,
          "down_count": 0
        },
        {
          "id": 12150,
          "important": false,
          "monitor_id": 6,
          "status": 1,
          "msg": "200 - OK",
          "time": "2025-12-31 11:13:46.440",
          "ping": 109,
          "duration": 60,
          "down_count": 0
        },
        {
          "id": 12153,
          "important": false,
          "monitor_id": 6,
          "status": 1,
          "msg": "200 - OK",
          "time": "2025-12-31 11:14:46.553",
          "ping": 120,
          "duration": 60,
          "down_count": 0
        },
        {
          "id": 12156,
          "important": false,
          "monitor_id": 6,
          "status": 1,
          "msg": "200 - OK",
          "time": "2025-12-31 11:15:46.678",
          "ping": 101,
          "duration": 60,
          "down_count": 0
        },
        {
          "id": 12159,
          "important": false,
          "monitor_id": 6,
          "status": 1,
          "msg": "200 - OK",
          "time": "2025-12-31 11:16:46.785",
          "ping": 110,
          "duration": 60,
          "down_count": 0
        },
        {
          "id": 12162,
          "important": false,
          "monitor_id": 6,
          "status": 1,
          "msg": "200 - OK",
          "time": "2025-12-31 11:17:46.898",
          "ping": 103,
          "duration": 60,
          "down_count": 0
        },
        {
          "id": 12165,
          "important": false,
          "monitor_id": 6,
          "status": 1,
          "msg": "200 - OK",
          "time": "2025-12-31 11:18:47.006",
          "ping": 116,
          "duration": 60,
          "down_count": 0
        },
        {
          "id": 12168,
          "important": false,
          "monitor_id": 6,
          "status": 1,
          "msg": "200 - OK",
          "time": "2025-12-31 11:19:47.126",
          "ping": 102,
          "duration": 60,
          "down_count": 0
        },
        {
          "id": 12171,
          "important": false,
          "monitor_id": 6,
          "status": 1,
          "msg": "200 - OK",
          "time": "2025-12-31 11:20:47.232",
          "ping": 102,
          "duration": 60,
          "down_count": 0
        },
        {
          "id": 12174,
          "important": false,
          "monitor_id": 6,
          "status": 1,
          "msg": "200 - OK",
          "time": "2025-12-31 11:21:47.340",
          "ping": 102,
          "duration": 60,
          "down_count": 0
        },
        {
          "id": 12177,
          "important": false,
          "monitor_id": 6,
          "status": 1,
          "msg": "200 - OK",
          "time": "2025-12-31 11:22:47.446",
          "ping": 103,
          "duration": 60,
          "down_count": 0
        },
        {
          "id": 12180,
          "important": false,
          "monitor_id": 6,
          "status": 1,
          "msg": "200 - OK",
          "time": "2025-12-31 11:23:47.552",
          "ping": 118,
          "duration": 60,
          "down_count": 0
        },
        {
          "id": 12183,
          "important": false,
          "monitor_id": 6,
          "status": 1,
          "msg": "200 - OK",
          "time": "2025-12-31 11:24:47.674",
          "ping": 107,
          "duration": 60,
          "down_count": 0
        }
      ]
    },
    "7": {
      "monitor": {
        "id": 7,
        "name": "Verify/ Min",
        "type": "MonitorType.HTTP",
        "active": true
      },
      "count": 100,
      "beats": [
        {
          "id": 11884,
          "important": false,
          "monitor_id": 7,
          "status": 0,
          "msg": "Request failed with status code 410",
          "time": "2025-12-31 09:44:53.810",
          "ping": null,
          "duration": 60,
          "down_count": 0
        },
        {
          "id": 11887,
          "important": false,
          "monitor_id": 7,
          "status": 0,
          "msg": "Request failed with status code 410",
          "time": "2025-12-31 09:45:53.825",
          "ping": null,
          "duration": 60,
          "down_count": 0
        },
        {
          "id": 11890,
          "important": false,
          "monitor_id": 7,
          "status": 0,
          "msg": "Request failed with status code 410",
          "time": "2025-12-31 09:46:53.840",
          "ping": null,
          "duration": 60,
          "down_count": 0
        },
        {
          "id": 11893,
          "important": false,
          "monitor_id": 7,
          "status": 0,
          "msg": "Request failed with status code 410",
          "time": "2025-12-31 09:47:53.856",
          "ping": null,
          "duration": 60,
          "down_count": 0
        },
        {
          "id": 11896,
          "important": false,
          "monitor_id": 7,
          "status": 0,
          "msg": "Request failed with status code 410",
          "time": "2025-12-31 09:48:53.869",
          "ping": null,
          "duration": 60,
          "down_count": 0
        },
        {
          "id": 11899,
          "important": false,
          "monitor_id": 7,
          "status": 0,
          "msg": "Request failed with status code 410",
          "time": "2025-12-31 09:49:53.888",
          "ping": null,
          "duration": 60,
          "down_count": 0
        },
        {
          "id": 11902,
          "important": false,
          "monitor_id": 7,
          "status": 0,
          "msg": "Request failed with status code 410",
          "time": "2025-12-31 09:50:53.902",
          "ping": null,
          "duration": 60,
          "down_count": 0
        },
        {
          "id": 11905,
          "important": false,
          "monitor_id": 7,
          "status": 0,
          "msg": "Request failed with status code 410",
          "time": "2025-12-31 09:51:53.918",
          "ping": null,
          "duration": 60,
          "down_count": 0
        },
        {
          "id": 11908,
          "important": false,
          "monitor_id": 7,
          "status": 0,
          "msg": "Request failed with status code 410",
          "time": "2025-12-31 09:52:53.937",
          "ping": null,
          "duration": 60,
          "down_count": 0
        },
        {
          "id": 11911,
          "important": false,
          "monitor_id": 7,
          "status": 0,
          "msg": "Request failed with status code 410",
          "time": "2025-12-31 09:53:53.955",
          "ping": null,
          "duration": 60,
          "down_count": 0
        },
        {
          "id": 11914,
          "important": false,
          "monitor_id": 7,
          "status": 0,
          "msg": "Request failed with status code 410",
          "time": "2025-12-31 09:54:53.972",
          "ping": null,
          "duration": 60,
          "down_count": 0
        },
        {
          "id": 11917,
          "important": false,
          "monitor_id": 7,
          "status": 0,
          "msg": "Request failed with status code 410",
          "time": "2025-12-31 09:55:53.997",
          "ping": null,
          "duration": 60,
          "down_count": 0
        },
        {
          "id": 11920,
          "important": false,
          "monitor_id": 7,
          "status": 0,
          "msg": "Request failed with status code 410",
          "time": "2025-12-31 09:56:54.017",
          "ping": null,
          "duration": 60,
          "down_count": 0
        },
        {
          "id": 11923,
          "important": false,
          "monitor_id": 7,
          "status": 0,
          "msg": "Request failed with status code 410",
          "time": "2025-12-31 09:57:54.037",
          "ping": null,
          "duration": 60,
          "down_count": 0
        },
        {
          "id": 11926,
          "important": false,
          "monitor_id": 7,
          "status": 0,
          "msg": "Request failed with status code 410",
          "time": "2025-12-31 09:58:54.054",
          "ping": null,
          "duration": 60,
          "down_count": 0
        },
        {
          "id": 11929,
          "important": false,
          "monitor_id": 7,
          "status": 0,
          "msg": "Request failed with status code 410",
          "time": "2025-12-31 09:59:54.069",
          "ping": null,
          "duration": 60,
          "down_count": 0
        },
        {
          "id": 11932,
          "important": false,
          "monitor_id": 7,
          "status": 0,
          "msg": "Request failed with status code 410",
          "time": "2025-12-31 10:00:54.087",
          "ping": null,
          "duration": 60,
          "down_count": 0
        },
        {
          "id": 11935,
          "important": false,
          "monitor_id": 7,
          "status": 0,
          "msg": "Request failed with status code 410",
          "time": "2025-12-31 10:01:54.101",
          "ping": null,
          "duration": 60,
          "down_count": 0
        },
        {
          "id": 11938,
          "important": false,
          "monitor_id": 7,
          "status": 0,
          "msg": "Request failed with status code 410",
          "time": "2025-12-31 10:02:54.116",
          "ping": null,
          "duration": 60,
          "down_count": 0
        },
        {
          "id": 11941,
          "important": false,
          "monitor_id": 7,
          "status": 0,
          "msg": "Request failed with status code 410",
          "time": "2025-12-31 10:03:54.132",
          "ping": null,
          "duration": 60,
          "down_count": 0
        },
        {
          "id": 11944,
          "important": false,
          "monitor_id": 7,
          "status": 0,
          "msg": "Request failed with status code 410",
          "time": "2025-12-31 10:04:54.169",
          "ping": null,
          "duration": 60,
          "down_count": 0
        },
        {
          "id": 11947,
          "important": false,
          "monitor_id": 7,
          "status": 0,
          "msg": "Request failed with status code 410",
          "time": "2025-12-31 10:05:54.185",
          "ping": null,
          "duration": 60,
          "down_count": 0
        },
        {
          "id": 11950,
          "important": false,
          "monitor_id": 7,
          "status": 0,
          "msg": "Request failed with status code 410",
          "time": "2025-12-31 10:06:54.199",
          "ping": null,
          "duration": 60,
          "down_count": 0
        },
        {
          "id": 11953,
          "important": false,
          "monitor_id": 7,
          "status": 0,
          "msg": "Request failed with status code 410",
          "time": "2025-12-31 10:07:54.213",
          "ping": null,
          "duration": 60,
          "down_count": 0
        },
        {
          "id": 11956,
          "important": false,
          "monitor_id": 7,
          "status": 0,
          "msg": "Request failed with status code 410",
          "time": "2025-12-31 10:08:54.230",
          "ping": null,
          "duration": 60,
          "down_count": 0
        },
        {
          "id": 11959,
          "important": false,
          "monitor_id": 7,
          "status": 0,
          "msg": "Request failed with status code 410",
          "time": "2025-12-31 10:09:54.261",
          "ping": null,
          "duration": 60,
          "down_count": 0
        },
        {
          "id": 11962,
          "important": false,
          "monitor_id": 7,
          "status": 0,
          "msg": "Request failed with status code 410",
          "time": "2025-12-31 10:10:54.279",
          "ping": null,
          "duration": 60,
          "down_count": 0
        },
        {
          "id": 11965,
          "important": false,
          "monitor_id": 7,
          "status": 0,
          "msg": "Request failed with status code 410",
          "time": "2025-12-31 10:11:54.298",
          "ping": null,
          "duration": 60,
          "down_count": 0
        },
        {
          "id": 11968,
          "important": false,
          "monitor_id": 7,
          "status": 0,
          "msg": "Request failed with status code 410",
          "time": "2025-12-31 10:12:54.316",
          "ping": null,
          "duration": 60,
          "down_count": 0
        },
        {
          "id": 11971,
          "important": false,
          "monitor_id": 7,
          "status": 0,
          "msg": "Request failed with status code 410",
          "time": "2025-12-31 10:13:54.335",
          "ping": null,
          "duration": 60,
          "down_count": 0
        },
        {
          "id": 11974,
          "important": false,
          "monitor_id": 7,
          "status": 0,
          "msg": "Request failed with status code 410",
          "time": "2025-12-31 10:14:54.349",
          "ping": null,
          "duration": 60,
          "down_count": 0
        },
        {
          "id": 11977,
          "important": false,
          "monitor_id": 7,
          "status": 0,
          "msg": "Request failed with status code 410",
          "time": "2025-12-31 10:15:54.366",
          "ping": null,
          "duration": 60,
          "down_count": 0
        },
        {
          "id": 11980,
          "important": false,
          "monitor_id": 7,
          "status": 0,
          "msg": "Request failed with status code 410",
          "time": "2025-12-31 10:16:54.385",
          "ping": null,
          "duration": 60,
          "down_count": 0
        },
        {
          "id": 11983,
          "important": false,
          "monitor_id": 7,
          "status": 0,
          "msg": "Request failed with status code 410",
          "time": "2025-12-31 10:17:54.402",
          "ping": null,
          "duration": 60,
          "down_count": 0
        },
        {
          "id": 11986,
          "important": false,
          "monitor_id": 7,
          "status": 0,
          "msg": "Request failed with status code 410",
          "time": "2025-12-31 10:18:54.420",
          "ping": null,
          "duration": 60,
          "down_count": 0
        },
        {
          "id": 11989,
          "important": false,
          "monitor_id": 7,
          "status": 0,
          "msg": "Request failed with status code 410",
          "time": "2025-12-31 10:19:54.469",
          "ping": null,
          "duration": 60,
          "down_count": 0
        },
        {
          "id": 11992,
          "important": false,
          "monitor_id": 7,
          "status": 0,
          "msg": "Request failed with status code 410",
          "time": "2025-12-31 10:20:54.491",
          "ping": null,
          "duration": 60,
          "down_count": 0
        },
        {
          "id": 11995,
          "important": false,
          "monitor_id": 7,
          "status": 0,
          "msg": "Request failed with status code 410",
          "time": "2025-12-31 10:21:54.520",
          "ping": null,
          "duration": 60,
          "down_count": 0
        },
        {
          "id": 11998,
          "important": false,
          "monitor_id": 7,
          "status": 0,
          "msg": "Request failed with status code 410",
          "time": "2025-12-31 10:22:54.534",
          "ping": null,
          "duration": 60,
          "down_count": 0
        },
        {
          "id": 12001,
          "important": false,
          "monitor_id": 7,
          "status": 0,
          "msg": "Request failed with status code 410",
          "time": "2025-12-31 10:23:54.550",
          "ping": null,
          "duration": 60,
          "down_count": 0
        },
        {
          "id": 12004,
          "important": false,
          "monitor_id": 7,
          "status": 0,
          "msg": "Request failed with status code 410",
          "time": "2025-12-31 10:24:54.567",
          "ping": null,
          "duration": 60,
          "down_count": 0
        },
        {
          "id": 12007,
          "important": false,
          "monitor_id": 7,
          "status": 0,
          "msg": "Request failed with status code 410",
          "time": "2025-12-31 10:25:54.627",
          "ping": null,
          "duration": 60,
          "down_count": 0
        },
        {
          "id": 12010,
          "important": false,
          "monitor_id": 7,
          "status": 0,
          "msg": "Request failed with status code 410",
          "time": "2025-12-31 10:26:54.641",
          "ping": null,
          "duration": 60,
          "down_count": 0
        },
        {
          "id": 12013,
          "important": false,
          "monitor_id": 7,
          "status": 0,
          "msg": "Request failed with status code 410",
          "time": "2025-12-31 10:27:54.657",
          "ping": null,
          "duration": 60,
          "down_count": 0
        },
        {
          "id": 12016,
          "important": false,
          "monitor_id": 7,
          "status": 0,
          "msg": "Request failed with status code 410",
          "time": "2025-12-31 10:28:54.677",
          "ping": null,
          "duration": 60,
          "down_count": 0
        },
        {
          "id": 12019,
          "important": false,
          "monitor_id": 7,
          "status": 0,
          "msg": "Request failed with status code 410",
          "time": "2025-12-31 10:29:54.695",
          "ping": null,
          "duration": 60,
          "down_count": 0
        },
        {
          "id": 12022,
          "important": false,
          "monitor_id": 7,
          "status": 0,
          "msg": "Request failed with status code 410",
          "time": "2025-12-31 10:30:54.709",
          "ping": null,
          "duration": 60,
          "down_count": 0
        },
        {
          "id": 12025,
          "important": false,
          "monitor_id": 7,
          "status": 0,
          "msg": "Request failed with status code 410",
          "time": "2025-12-31 10:31:54.726",
          "ping": null,
          "duration": 60,
          "down_count": 0
        },
        {
          "id": 12028,
          "important": false,
          "monitor_id": 7,
          "status": 0,
          "msg": "Request failed with status code 410",
          "time": "2025-12-31 10:32:54.740",
          "ping": null,
          "duration": 60,
          "down_count": 0
        },
        {
          "id": 12031,
          "important": false,
          "monitor_id": 7,
          "status": 0,
          "msg": "Request failed with status code 410",
          "time": "2025-12-31 10:33:54.757",
          "ping": null,
          "duration": 60,
          "down_count": 0
        },
        {
          "id": 12034,
          "important": false,
          "monitor_id": 7,
          "status": 0,
          "msg": "Request failed with status code 410",
          "time": "2025-12-31 10:34:54.771",
          "ping": null,
          "duration": 60,
          "down_count": 0
        },
        {
          "id": 12037,
          "important": false,
          "monitor_id": 7,
          "status": 0,
          "msg": "Request failed with status code 410",
          "time": "2025-12-31 10:35:54.787",
          "ping": null,
          "duration": 60,
          "down_count": 0
        },
        {
          "id": 12040,
          "important": false,
          "monitor_id": 7,
          "status": 0,
          "msg": "Request failed with status code 410",
          "time": "2025-12-31 10:36:54.805",
          "ping": null,
          "duration": 60,
          "down_count": 0
        },
        {
          "id": 12043,
          "important": false,
          "monitor_id": 7,
          "status": 0,
          "msg": "Request failed with status code 410",
          "time": "2025-12-31 10:37:54.822",
          "ping": null,
          "duration": 60,
          "down_count": 0
        },
        {
          "id": 12046,
          "important": false,
          "monitor_id": 7,
          "status": 0,
          "msg": "Request failed with status code 410",
          "time": "2025-12-31 10:38:54.838",
          "ping": null,
          "duration": 60,
          "down_count": 0
        },
        {
          "id": 12049,
          "important": false,
          "monitor_id": 7,
          "status": 0,
          "msg": "Request failed with status code 410",
          "time": "2025-12-31 10:39:54.854",
          "ping": null,
          "duration": 60,
          "down_count": 0
        },
        {
          "id": 12052,
          "important": false,
          "monitor_id": 7,
          "status": 0,
          "msg": "Request failed with status code 410",
          "time": "2025-12-31 10:40:54.872",
          "ping": null,
          "duration": 60,
          "down_count": 0
        },
        {
          "id": 12055,
          "important": false,
          "monitor_id": 7,
          "status": 0,
          "msg": "Request failed with status code 410",
          "time": "2025-12-31 10:41:54.886",
          "ping": null,
          "duration": 60,
          "down_count": 0
        },
        {
          "id": 12058,
          "important": false,
          "monitor_id": 7,
          "status": 0,
          "msg": "Request failed with status code 410",
          "time": "2025-12-31 10:42:54.897",
          "ping": null,
          "duration": 60,
          "down_count": 0
        },
        {
          "id": 12061,
          "important": false,
          "monitor_id": 7,
          "status": 0,
          "msg": "Request failed with status code 410",
          "time": "2025-12-31 10:43:54.916",
          "ping": null,
          "duration": 60,
          "down_count": 0
        },
        {
          "id": 12064,
          "important": false,
          "monitor_id": 7,
          "status": 0,
          "msg": "Request failed with status code 410",
          "time": "2025-12-31 10:44:54.933",
          "ping": null,
          "duration": 60,
          "down_count": 0
        },
        {
          "id": 12067,
          "important": false,
          "monitor_id": 7,
          "status": 0,
          "msg": "Request failed with status code 410",
          "time": "2025-12-31 10:45:54.949",
          "ping": null,
          "duration": 60,
          "down_count": 0
        },
        {
          "id": 12070,
          "important": false,
          "monitor_id": 7,
          "status": 0,
          "msg": "Request failed with status code 410",
          "time": "2025-12-31 10:46:54.966",
          "ping": null,
          "duration": 60,
          "down_count": 0
        },
        {
          "id": 12073,
          "important": false,
          "monitor_id": 7,
          "status": 0,
          "msg": "Request failed with status code 410",
          "time": "2025-12-31 10:47:54.991",
          "ping": null,
          "duration": 60,
          "down_count": 0
        },
        {
          "id": 12076,
          "important": false,
          "monitor_id": 7,
          "status": 0,
          "msg": "Request failed with status code 410",
          "time": "2025-12-31 10:48:55.003",
          "ping": null,
          "duration": 60,
          "down_count": 0
        },
        {
          "id": 12079,
          "important": false,
          "monitor_id": 7,
          "status": 0,
          "msg": "Request failed with status code 410",
          "time": "2025-12-31 10:49:55.018",
          "ping": null,
          "duration": 60,
          "down_count": 0
        },
        {
          "id": 12082,
          "important": false,
          "monitor_id": 7,
          "status": 0,
          "msg": "Request failed with status code 410",
          "time": "2025-12-31 10:50:55.032",
          "ping": null,
          "duration": 60,
          "down_count": 0
        },
        {
          "id": 12085,
          "important": false,
          "monitor_id": 7,
          "status": 0,
          "msg": "Request failed with status code 410",
          "time": "2025-12-31 10:51:55.049",
          "ping": null,
          "duration": 60,
          "down_count": 0
        },
        {
          "id": 12088,
          "important": false,
          "monitor_id": 7,
          "status": 0,
          "msg": "Request failed with status code 410",
          "time": "2025-12-31 10:52:55.062",
          "ping": null,
          "duration": 60,
          "down_count": 0
        },
        {
          "id": 12091,
          "important": false,
          "monitor_id": 7,
          "status": 0,
          "msg": "Request failed with status code 410",
          "time": "2025-12-31 10:53:55.079",
          "ping": null,
          "duration": 60,
          "down_count": 0
        },
        {
          "id": 12094,
          "important": false,
          "monitor_id": 7,
          "status": 0,
          "msg": "Request failed with status code 410",
          "time": "2025-12-31 10:54:55.096",
          "ping": null,
          "duration": 60,
          "down_count": 0
        },
        {
          "id": 12097,
          "important": false,
          "monitor_id": 7,
          "status": 0,
          "msg": "Request failed with status code 410",
          "time": "2025-12-31 10:55:55.112",
          "ping": null,
          "duration": 60,
          "down_count": 0
        },
        {
          "id": 12100,
          "important": false,
          "monitor_id": 7,
          "status": 0,
          "msg": "Request failed with status code 410",
          "time": "2025-12-31 10:56:55.127",
          "ping": null,
          "duration": 60,
          "down_count": 0
        },
        {
          "id": 12103,
          "important": false,
          "monitor_id": 7,
          "status": 0,
          "msg": "Request failed with status code 410",
          "time": "2025-12-31 10:57:55.143",
          "ping": null,
          "duration": 60,
          "down_count": 0
        },
        {
          "id": 12106,
          "important": false,
          "monitor_id": 7,
          "status": 0,
          "msg": "Request failed with status code 410",
          "time": "2025-12-31 10:58:55.157",
          "ping": null,
          "duration": 60,
          "down_count": 0
        },
        {
          "id": 12109,
          "important": false,
          "monitor_id": 7,
          "status": 0,
          "msg": "Request failed with status code 410",
          "time": "2025-12-31 10:59:55.173",
          "ping": null,
          "duration": 60,
          "down_count": 0
        },
        {
          "id": 12112,
          "important": false,
          "monitor_id": 7,
          "status": 0,
          "msg": "Request failed with status code 410",
          "time": "2025-12-31 11:00:55.189",
          "ping": null,
          "duration": 60,
          "down_count": 0
        },
        {
          "id": 12115,
          "important": false,
          "monitor_id": 7,
          "status": 0,
          "msg": "Request failed with status code 410",
          "time": "2025-12-31 11:01:55.204",
          "ping": null,
          "duration": 60,
          "down_count": 0
        },
        {
          "id": 12118,
          "important": false,
          "monitor_id": 7,
          "status": 0,
          "msg": "Request failed with status code 410",
          "time": "2025-12-31 11:02:55.226",
          "ping": null,
          "duration": 60,
          "down_count": 0
        },
        {
          "id": 12121,
          "important": false,
          "monitor_id": 7,
          "status": 0,
          "msg": "Request failed with status code 410",
          "time": "2025-12-31 11:03:55.244",
          "ping": null,
          "duration": 60,
          "down_count": 0
        },
        {
          "id": 12124,
          "important": false,
          "monitor_id": 7,
          "status": 0,
          "msg": "Request failed with status code 410",
          "time": "2025-12-31 11:04:55.264",
          "ping": null,
          "duration": 60,
          "down_count": 0
        },
        {
          "id": 12127,
          "important": false,
          "monitor_id": 7,
          "status": 0,
          "msg": "Request failed with status code 410",
          "time": "2025-12-31 11:05:55.281",
          "ping": null,
          "duration": 60,
          "down_count": 0
        },
        {
          "id": 12130,
          "important": false,
          "monitor_id": 7,
          "status": 0,
          "msg": "Request failed with status code 410",
          "time": "2025-12-31 11:06:55.298",
          "ping": null,
          "duration": 60,
          "down_count": 0
        },
        {
          "id": 12133,
          "important": false,
          "monitor_id": 7,
          "status": 0,
          "msg": "Request failed with status code 410",
          "time": "2025-12-31 11:07:55.313",
          "ping": null,
          "duration": 60,
          "down_count": 0
        },
        {
          "id": 12136,
          "important": false,
          "monitor_id": 7,
          "status": 0,
          "msg": "Request failed with status code 410",
          "time": "2025-12-31 11:08:55.327",
          "ping": null,
          "duration": 60,
          "down_count": 0
        },
        {
          "id": 12139,
          "important": false,
          "monitor_id": 7,
          "status": 0,
          "msg": "Request failed with status code 410",
          "time": "2025-12-31 11:09:55.352",
          "ping": null,
          "duration": 60,
          "down_count": 0
        },
        {
          "id": 12142,
          "important": false,
          "monitor_id": 7,
          "status": 0,
          "msg": "Request failed with status code 410",
          "time": "2025-12-31 11:10:55.370",
          "ping": null,
          "duration": 60,
          "down_count": 0
        },
        {
          "id": 12145,
          "important": false,
          "monitor_id": 7,
          "status": 0,
          "msg": "Request failed with status code 410",
          "time": "2025-12-31 11:11:55.386",
          "ping": null,
          "duration": 60,
          "down_count": 0
        },
        {
          "id": 12148,
          "important": false,
          "monitor_id": 7,
          "status": 0,
          "msg": "Request failed with status code 410",
          "time": "2025-12-31 11:12:55.403",
          "ping": null,
          "duration": 60,
          "down_count": 0
        },
        {
          "id": 12151,
          "important": false,
          "monitor_id": 7,
          "status": 0,
          "msg": "Request failed with status code 410",
          "time": "2025-12-31 11:13:55.417",
          "ping": null,
          "duration": 60,
          "down_count": 0
        },
        {
          "id": 12154,
          "important": false,
          "monitor_id": 7,
          "status": 0,
          "msg": "Request failed with status code 410",
          "time": "2025-12-31 11:14:55.433",
          "ping": null,
          "duration": 60,
          "down_count": 0
        },
        {
          "id": 12157,
          "important": false,
          "monitor_id": 7,
          "status": 0,
          "msg": "Request failed with status code 410",
          "time": "2025-12-31 11:15:55.450",
          "ping": null,
          "duration": 60,
          "down_count": 0
        },
        {
          "id": 12160,
          "important": false,
          "monitor_id": 7,
          "status": 0,
          "msg": "Request failed with status code 410",
          "time": "2025-12-31 11:16:55.467",
          "ping": null,
          "duration": 60,
          "down_count": 0
        },
        {
          "id": 12163,
          "important": false,
          "monitor_id": 7,
          "status": 0,
          "msg": "Request failed with status code 410",
          "time": "2025-12-31 11:17:55.485",
          "ping": null,
          "duration": 60,
          "down_count": 0
        },
        {
          "id": 12166,
          "important": false,
          "monitor_id": 7,
          "status": 0,
          "msg": "Request failed with status code 410",
          "time": "2025-12-31 11:18:55.498",
          "ping": null,
          "duration": 60,
          "down_count": 0
        },
        {
          "id": 12169,
          "important": false,
          "monitor_id": 7,
          "status": 0,
          "msg": "Request failed with status code 410",
          "time": "2025-12-31 11:19:55.511",
          "ping": null,
          "duration": 60,
          "down_count": 0
        },
        {
          "id": 12172,
          "important": false,
          "monitor_id": 7,
          "status": 0,
          "msg": "Request failed with status code 410",
          "time": "2025-12-31 11:20:55.526",
          "ping": null,
          "duration": 60,
          "down_count": 0
        },
        {
          "id": 12175,
          "important": false,
          "monitor_id": 7,
          "status": 0,
          "msg": "Request failed with status code 410",
          "time": "2025-12-31 11:21:55.546",
          "ping": null,
          "duration": 60,
          "down_count": 0
        },
        {
          "id": 12178,
          "important": false,
          "monitor_id": 7,
          "status": 0,
          "msg": "Request failed with status code 410",
          "time": "2025-12-31 11:22:55.564",
          "ping": null,
          "duration": 60,
          "down_count": 0
        },
        {
          "id": 12181,
          "important": false,
          "monitor_id": 7,
          "status": 0,
          "msg": "Request failed with status code 410",
          "time": "2025-12-31 11:23:55.578",
          "ping": null,
          "duration": 60,
          "down_count": 0
        }
      ]
    }
  }
}